Workbook

Sheet Sheet1
A1: MDA'S MOTOR-VEHICLE DEDUCTION RETURNS AS AT APRIL, 2020.
A2: S/N | B2: REF. I.D | C2: STAFF NAME | D2: PRINCIPAL N | E2: INTEREST N | F2: TOTAL LOAN N | G2: NO. OF. INSTL. | H2: MONTHLY DED N | I2: MONTHLY INTEREST | J2: MONTHLY PRINCIPAL | K2: TOTAL INTEREST PAID | L2: TOTAL OUTSTANDING INTEREST | M2: NO. OF INSTAL. PAID | N2: NO. OF INSTAL. OUTS. | O2: TOTAL LOAN PAID N | P2: OUTS. BAL. N | Q2: REMARK | S2: NO. OF INSTAL. PAID | T2: NO. OF INSTAL. OUTS. | U2: TOTAL LOAN PAID N | V2: OUTS. BAL. N
A3: 1 | B3: 0 | C3: MR. A. A. OLADOJA | D3: 500000 | E3: =D3*0.1333 -> 66650 | F3: =D3+E3 -> 566650 | G3: 50 | H3: 11333 | I3: =E3/G3 -> 1333 | J3: =D3/G3 -> 10000 | K3: =M3*I3 -> 17329 | L3: =I3*N3 -> 49321 | M3: =S3+R3 -> 13 | N3: =T3-R3 -> 37 | O3: =U3+H3 -> 147328 | P3: =V3-H3 -> 407988 | R3: 1 | S3: 12 | T3: 38 | U3: 135995 | V3: 419321 | Z3: ACCOUNT
A4: 2 | B4: 0 | C4: ADENUGA JUMOKE A. | D4: 600000 | E4: =D4*0.1333 -> 79980 | F4: =D4+E4 -> 679980 | G4: 50 | H4: 13333 | I4: =E4/G4 -> 1599.6 | J4: =D4/G4 -> 12000 | K4: =M4*I4 -> 70382.4 | L4: =I4*N4 -> 11197.2 | M4: =S4+R4 -> 44 | N4: =T4-R4 -> 7 | O4: =U4+H4 -> 327483.76 | P4: =V4-H4 -> 639984 | R4: 1 | S4: 43 | T4: 8 | U4: 314150.76 | V4: 653317 | Y4: 12034.94
A5: 3 | B5: 0 | C5: ALABI FUNMILAYO S. | D5: 330000 | E5: =D5*0.1333 -> 43989 | F5: =D5+E5 -> 373989 | G5: 50 | H5: 7479.78 | I5: =E5/G5 -> 879.78 | J5: =D5/G5 -> 6600 | K5: =M5*I5 -> 44868.78 | L5: =I5*N5 -> 0 | M5: =S5+R5 -> 51 | N5: =T5-R5 -> 0 | O5: =U5+H5 -> 329110.32 | P5: =V5-H5 -> 44878.68 | R5: 1 | S5: 50 | T5: 1 | U5: 321630.54 | V5: 52358.46
A6: 4 | B6: 0 | C6: MR. OLUSEYE ABODERIN | D6: 450000 | E6: =D6*0.1333 -> 59985 | F6: =D6+E6 -> 509985 | G6: 50 | H6: 10199.7 | I6: =E6/G6 -> 1199.7 | J6: =D6/G6 -> 9000 | K6: =M6*I6 -> 19195.2 | L6: =I6*N6 -> 40789.8 | M6: =S6+R6 -> 16 | N6: =T6-R6 -> 34 | O6: =U6+H6 -> 173394.9 | P6: =V6-H6 -> 346789.8 | R6: 1 | S6: 15 | T6: 35 | U6: 163195.2 | V6: 356989.5
A7: 5 | C7: MRS. A. B. FOLAHAN | D7: 150000 | E7: =D7*0.1333 -> 19995 | F7: =D7+E7 -> 169995 | G7: 50 | H7: 3399.9 | I7: =E7/G7 -> 399.9 | J7: =D7/G7 -> 3000 | K7: =M7*I7 -> 4798.8 | L7: =I7*N7 -> 15196.2 | M7: =S7+R7 -> 12 | N7: =T7-R7 -> 38 | O7: =U7+H7 -> 40798.8 | P7: =V7-H7 -> 129196.2 | R7: 1 | S7: 11 | T7: 39 | U7: 37398.9 | V7: 132596.1 | X7: =SUM(H3:H7) -> 45745.38 | AD7: 0
A8: 6 | B8: 0 | C8: MR. I. J. OLAGUNJU | D8: 330000 | E8: =D8*0.1333 -> 43989 | F8: =D8+E8 -> 373989 | G8: 50 | H8: 7479.78 | I8: =E8/G8 -> 879.78 | J8: =D8/G8 -> 6600 | K8: =M8*I8 -> 35191.2 | L8: =I8*N8 -> 9677.58 | M8: =S8+R8 -> 40 | N8: =T8-R8 -> 11 | O8: =U8+H8 -> 291711.42 | P8: =V8-H8 -> 82277.58 | R8: 1 | S8: 39 | T8: 12 | U8: 284231.64 | V8: 89757.36 | Z8: APPEAL
A9: 7 | C9: MRS. B. O. SOMIDE | D9: 450000 | E9: =D9*0.1333 -> 59985 | F9: =D9+E9 -> 509985 | G9: 50 | H9: 10199.7 | I9: =E9/G9 -> 1199.7 | J9: =D9/G9 -> 9000 | K9: =M9*I9 -> 5998.5 | L9: =I9*N9 -> 53986.5 | M9: =S9+R9 -> 5 | N9: =T9-R9 -> 45 | O9: =U9+H9 -> 50998.5 | P9: =V9-H9 -> 458986.5 | R9: 1 | S9: 4 | T9: 46 | U9: 40798.8 | V9: 469186.2
A10: 8 | C10: MRS O.F. STANLEY JOHN | D10: 450000 | E10: =D10*0.1333 -> 59985 | F10: =D10+E10 -> 509985 | G10: 50 | H10: 13699.7 | I10: =E10/G10 -> 1199.7 | J10: =D10/G10 -> 9000 | K10: =M10*I10 -> 2399.4 | L10: =I10*N10 -> 57585.6 | M10: =S10+R10 -> 2 | N10: =T10-R10 -> 48 | O10: =U10+H10 -> 27399.4 | P10: =V10-H10 -> 482585.6 | R10: 1 | S10: 1 | T10: 49 | U10: 13699.7 | V10: 496285.3 | X10: =SUM(H8:H10) -> 31379.18
A11: 9 | C11: MRS ADEYEYE-KUKU O.O | D11: 450000 | E11: =D11*0.1333 -> 59985 | F11: =D11+E11 -> 509985 | G11: 50 | H11: 9999.75 | I11: =E11/G11 -> 1199.7 | J11: =D11/G11 -> 9000 | K11: =M11*I11 -> 3599.1 | L11: =I11*N11 -> 56385.9 | M11: =S11+R11 -> 3 | N11: =T11-R11 -> 47 | O11: =U11+H11 -> 19999.5 | P11: 489987.75 | R11: 1 | S11: 2 | T11: 48 | U11: 9999.75 | V11: 489987.75 | Z11: AUDIT
A12: 10 | C12: MR. J. O. AWOTUNDE | D12: 330000 | E12: =D12*0.13333 -> 43998.9 | F12: =D12+E12 -> 373998.9 | G12: 37 | H12: 10000 | I12: =E12/G12 -> 1189.1595 | J12: =D12/G12 -> 8918.9189 | K12: =M12*I12 -> 8324.1162 | L12: =I12*N12 -> 51133.857 | M12: =S12+R12 -> 7 | N12: =T12-R12 -> 43 | O12: =U12+H12 -> 70000 | P12: =V12-H12 -> 303998.9 | R12: 1 | S12: 6 | T12: 44 | U12: 60000 | V12: 313998.9
A13: 11 | C13: MR. J. B. AYANKOSO | D13: 500000 | E13: =D13*0.13333 -> 66665 | F13: =D13+E13 -> 566665 | G13: 50 | H13: 11333 | I13: =E13/G13 -> 1333.3 | J13: =D13/G13 -> 10000 | K13: =M13*I13 -> 6666.5 | L13: =I13*N13 -> 59998.5 | M13: =S13+R13 -> 5 | N13: =T13-R13 -> 45 | O13: =U13+H13 -> 56665 | P13: =V13-H13 -> 510000 | R13: 1 | S13: 4 | T13: 46 | U13: 45332 | V13: 521333 | X13: =SUM(H11:H13) -> 31332.75
A14: 12 | B14: 0 | C14: OLASUNKANMI A. | D14: 450000 | E14: =D14*0.1333 -> 59985 | F14: =G14*H14 -> 509985 | G14: 50 | H14: 10199.7 | I14: =E14/G14 -> 1199.7 | J14: =D14/G14 -> 9000 | K14: =M14*I14 -> 61184.7 | L14: =I14*N14 -> 0 | M14: =S14+R14 -> 51 | N14: =T14-R14 -> 0 | O14: =U14+H14 -> 438587.1 | P14: =V14-H14 -> 71397.9 | R14: 1 | S14: 50 | T14: 1 | U14: 428387.4 | V14: 81597.6
A15: 13 | B15: 0 | C15: O. M. AKINLABI | D15: 150000 | E15: =D15*0.1333 -> 19995 | F15: =G15*H15 -> 169995 | G15: 50 | H15: 3399.9 | I15: =E15/G15 -> 399.9 | J15: =D15/G15 -> 3000 | K15: =M15*I15 -> 7598.1 | L15: =I15*N15 -> 12396.9 | M15: =S15+R15 -> 19 | N15: =T15-R15 -> 31 | O15: =U15+H15 -> 101994.3 | P15: =V15-H15 -> 68000.7 | R15: 1 | S15: 18 | T15: 32 | U15: 98594.4 | V15: 71400.6
A16: 14 | B16: 0 | C16: MR. OTITOLOJU O. ADISA | D16: 500000 | E16: =D16*0.1333 -> 66650 | F16: =G16*H16 -> 566650 | G16: 50 | H16: 11333 | I16: =E16/G16 -> 1333 | J16: =D16/G16 -> 10000 | K16: =M16*I16 -> 23994 | L16: =I16*N16 -> 42656 | M16: =S16+R16 -> 18 | N16: =T16-R16 -> 32 | O16: =U16+H16 -> 203994 | P16: =V16-H16 -> 362656 | R16: 1 | S16: 17 | T16: 33 | U16: 192661 | V16: 373989
A17: 15 | B17: 0 | C17: MRS. ADEUGA M.M. | D17: 500000 | E17: =D17*0.09 -> 45000 | F17: =G17*H17 -> 566650 | G17: 50 | H17: 11333 | I17: =E17/G17 -> 900 | J17: =D17/G17 -> 10000 | K17: =M17*I17 -> 16200 | L17: =I17*N17 -> 28800 | M17: =S17+R17 -> 18 | N17: =T17-R17 -> 32 | O17: =U17+H17 -> 203994 | P17: =V17-H17 -> 362656 | R17: 1 | S17: 17 | T17: 33 | U17: 192661 | V17: 373989
A18: 16 | B18: 0 | C18: MR. NASIRU A | D18: 330000 | E18: =D18*0.09 -> 29700 | F18: =G18*H18 -> 373989 | G18: 50 | H18: 7479.78 | I18: =E18/G18 -> 594 | J18: =D18/G18 -> 6600 | K18: =M18*I18 -> 10692 | L18: =I18*N18 -> 19008 | M18: =S18+R18 -> 18 | N18: =T18-R18 -> 32 | O18: =U18+H18 -> 134636.04 | P18: =V18-H18 -> 239352.96 | R18: 1 | S18: 17 | T18: 33 | U18: 127156.26 | V18: 246832.74
A19: 17 | C19: MISS. T. A. ADESOLA | D19: 450000 | E19: =D19*0.09 -> 40500 | F19: =G19*H19 -> 478800 | G19: 24 | H19: 19950 | I19: =E19/G19 -> 1687.5 | J19: =D19/G19 -> 18750 | K19: =M19*I19 -> 15187.5 | L19: =I19*N19 -> 69187.5 | M19: =S19+R19 -> 9 | N19: =T19-R19 -> 41 | O19: =U19+H19 -> 179550 | P19: =V19-H19 -> 299250 | R19: 1 | S19: 8 | T19: 42 | U19: 159600 | V19: 319200 | W19: CR'S
A20: 18 | C20: MRS. PATRICIA ADETUYIBI | D20: 500000 | E20: =D20*0.09 -> 45000 | F20: =G20*H20 -> 566650 | G20: 50 | H20: 11333 | I20: =E20/G20 -> 900 | J20: =D20/G20 -> 10000 | K20: =M20*I20 -> 11700 | L20: =I20*N20 -> 33300 | M20: =S20+R20 -> 13 | N20: =T20-R20 -> 37 | O20: =U20+H20 -> 147329 | P20: =V20-H20 -> 419321 | R20: 1 | S20: 12 | T20: 38 | U20: 135996 | V20: 430654
A21: 19 | C21: MRS. O. A. AKANDE | D21: 150000 | E21: =D21*0.09 -> 13500 | F21: =G21*H21 -> 169995 | G21: 50 | H21: 3399.9 | I21: =E21/G21 -> 270 | J21: =D21/G21 -> 3000 | K21: =M21*I21 -> 3240 | L21: =I21*N21 -> 10260 | M21: =S21+R21 -> 12 | N21: =T21-R21 -> 38 | O21: =U21+H21 -> 40798.8 | P21: =V21-H21 -> 129196.2 | R21: 1 | S21: 11 | T21: 39 | U21: 37398.9 | V21: 132596.1
A22: 20 | C22: MRS ADEROUNMU | D22: 500000 | E22: =D22*0.1333 -> 66650 | F22: =G22*H22 -> 527191.92 | G22: 24 | H22: 21966.33 | I22: =E22/G22 -> 2777.0833 | J22: =D22/G22 -> 20833.333 | K22: =M22*I22 -> 5554.1667 | L22: =I22*N22 -> 61095.833 | M22: =S22+R22 -> 2 | N22: =T22-R22 -> 22 | O22: =U22+H22 -> 43932.66 | P22: =V22-H22 -> 483259.34 | R22: 1 | S22: 1 | T22: 23 | U22: 21966.33 | V22: 505225.67
A23: 21 | C23: MR SHOMOYE T.H. | D23: 500000 | E23: =D23*0.1333 -> 66650 | F23: =G23*H23 -> 509985 | G23: 50 | H23: 10199.7 | I23: =E23/G23 -> 1333 | J23: =D23/G23 -> 10000 | K23: =M23*I23 -> 3999 | L23: =I23*N23 -> 63984 | M23: =S23+R23 -> 3 | N23: =T23-R23 -> 48 | O23: =U23+H23 -> 20399.4 | P23: =V23-H23 -> 495025.97 | R23: 1 | S23: 2 | T23: 49 | U23: 10199.7 | V23: 505225.67
A24: 22 | C24: MRS O.O ADENUGA | D24: 500000 | E24: =D24*0.1333 -> 66650 | F24: =G24*H24 -> 509985 | G24: 50 | H24: 10199.7 | I24: =E24/G24 -> 1333 | J24: =D24/G24 -> 10000 | K24: =M24*I24 -> 3999 | L24: =I24*N24 -> 63984 | M24: =S24+R24 -> 3 | N24: =T24-R24 -> 48 | O24: =U24+H24 -> 20399.4 | P24: 499785.3 | R24: 1 | S24: 2 | T24: 49 | U24: 10199.7 | V24: 505225.67
A25: 23 | C25: MISS A.O. ALIMI | D25: 500000 | E25: =D25*0.1333 -> 66650 | F25: =G25*H25 -> 684985 | G25: 50 | H25: 13699.7 | I25: =E25/G25 -> 1333 | J25: =D25/G25 -> 10000 | K25: =M25*I25 -> 3999 | L25: =I25*N25 -> 65317 | M25: =S25+R25 -> 3 | N25: 49 | O25: =U25+H25 -> 27399.4 | P25: =V25-H25 -> 491525.97 | R25: 1 | S25: 2 | T25: 49 | U25: 13699.7 | V25: 505225.67
A26: 24 | C26: FAMOKUN M.O. | D26: 500000 | E26: 66650 | F26: 509985 | G26: 50 | H26: 10199.7 | I26: 1333 | J26: 10000 | K26: 3999 | L26: 65317 | M26: 3 | N26: 49 | O26: 20399.4 | P26: 505225.67 | R26: 1 | S26: 2 | T26: 49 | U26: 10199.7 | V26: 505225.67 | X26: =SUM(H14:H26) -> 144693.41
A27: 25 | B27: 0 | C27: OLUSANYA FLORENCE O. | D27: 450000 | E27: =D27*0.1333 -> 59985 | F27: =G27*H27 -> 509985 | G27: 50 | H27: 10199.7 | I27: =E27/G27 -> 1199.7 | J27: =D27/G27 -> 9000 | K27: =M27*I27 -> 52786.8 | L27: =I27*N27 -> 8397.9 | M27: =S27+R27 -> 44 | N27: =T27-R27 -> 7 | O27: =U27+H27 -> 438687.1 | P27: =V27-H27 -> 71297.9 | R27: 1 | S27: 43 | T27: 8 | U27: 428487.4 | V27: 81497.6 | Z27: ESTAB
A28: 26 | B28: 0 | C28: OLAWORE MICHEAL F. | D28: 330000 | E28: =D28*0.1333 -> 43989 | F28: =G28*H28 -> 373989 | G28: 50 | H28: 7479.78 | I28: =E28/G28 -> 879.78 | J28: =D28/G28 -> 6600 | K28: =M28*I28 -> 38710.32 | L28: =I28*N28 -> 6158.46 | M28: =S28+R28 -> 44 | N28: =T28-R28 -> 7 | O28: =U28+H28 -> 321630.54 | P28: =V28-H28 -> 52358.46 | R28: 1 | S28: 43 | T28: 8 | U28: 314150.76 | V28: 59838.24
A29: 27 | C29: MRS. TAIWO O. ADEJUMO | D29: 330000 | E29: =D29*0.1333 -> 43989 | F29: =G29*H29 -> 373989 | G29: 50 | H29: 7479.78 | I29: =E29/G29 -> 879.78 | J29: =D29/G29 -> 6600 | K29: =M29*I29 -> 15836.04 | L29: =I29*N29 -> 28152.96 | M29: =S29+R29 -> 18 | N29: =T29-R29 -> 32 | O29: =U29+H29 -> 134636.04 | P29: =V29-H29 -> 239352.96 | R29: 1 | S29: 17 | T29: 33 | U29: 127156.26 | V29: 246832.74
A30: 28 | B30: 0 | C30: MRS. T. A. MOJEED | D30: 130000 | E30: =D30*0.1333 -> 17329 | F30: =G30*H30 -> 169995 | G30: 50 | H30: 3399.9 | I30: =E30/G30 -> 346.58 | J30: =D30/G30 -> 2600 | K30: =M30*I30 -> 346.58 | L30: =I30*N30 -> 16982.42 | M30: 1 | N30: 49 | O30: =U30+H30 -> 282191.7 | P30: =V30-H30 -> 64598.1 | R30: 1 | S30: 1 | T30: 49 | U30: 278791.8 | V30: 67998
A31: 29 | B31: 0 | C31: MR. KEHINDE ADEOSUN | D31: 450000 | E31: =D31*0.1333 -> 59985 | F31: =G31*H31 -> 509985 | G31: 50 | H31: 10199.7 | I31: =E31/G31 -> 1199.7 | J31: =D31/G31 -> 9000 | K31: =M31*I31 -> 20394.9 | L31: =I31*N31 -> 39590.1 | M31: =S31+R31 -> 17 | N31: =T31-R31 -> 33 | O31: =U31+H31 -> 173394.9 | P31: =V31-H31 -> 336590.1 | R31: 1 | S31: 16 | T31: 34 | U31: 163195.2 | V31: 346789.8
A32: 30 | C32: MRS. O. A. IDOWU | D32: 330000 | E32: =D32*0.1333 -> 43989 | F32: =G32*H32 -> 373989 | G32: 50 | H32: 7479.78 | I32: =E32/G32 -> 879.78 | J32: =D32/G32 -> 6600 | K32: =M32*I32 -> 4398.9 | L32: =I32*N32 -> 39590.1 | M32: =S32+R32 -> 5 | N32: =T32-R32 -> 45 | O32: =U32+H32 -> 37398.9 | P32: =V32-H32 -> 336590.1 | R32: 1 | S32: 4 | T32: 46 | U32: 29919.12 | V32: 344069.88
A33: 31 | C33: MRS O.T. ADESINA | D33: 330000 | E33: =D33*0.1333 -> 43989 | F33: =G33*H33 -> 373989 | G33: 50 | H33: 7479.78 | I33: =E33/G33 -> 879.78 | J33: =D33/G33 -> 6600 | K33: =M33*I33 -> 879.78 | L33: =I33*N33 -> 43109.22 | M33: 1 | N33: 49 | O33: =U33+H33 -> 14959.56 | P33: =V33-H33 -> 351549.66 | R33: 1 | S33: 1 | T33: 49 | U33: 7479.78 | V33: 359029.44 | X33: =SUM(H27:H33) -> 53718.42
A34: 32 | B34: 0 | C34: AKINYELE A. A.O. | D34: 500000 | E34: =D34*0.1333 -> 66650 | F34: =G34*H34 -> 400000 | G34: 50 | H34: 8000 | I34: =E34/G34 -> 1333 | J34: =D34/G34 -> 10000 | K34: =M34*I34 -> 67983 | L34: =I34*N34 -> 0 | M34: =S34+R34 -> 51 | N34: =T34-R34 -> 0 | O34: =U34+H34 -> 495319 | P34: =V34-H34 -> 71331 | R34: 1 | S34: 50 | T34: 1 | U34: 487319 | V34: 79331 | Z34: G40
A35: 33 | C35: MRS. M. A. BAMIRO | D35: 500000 | E35: =D35*0.1333 -> 66650 | F35: =G35*H35 -> 547984.8 | G35: 36 | H35: 15221.8 | I35: =E35/G35 -> 1851.3889 | J35: =D35/G35 -> 13888.889 | K35: =M35*I35 -> 24068.056 | L35: =I35*N35 -> 42581.944 | M35: =S35+R35 -> 13 | N35: =T35-R35 -> 23 | O35: =U35+H35 -> 197883.4 | P35: =V35-H35 -> 350101.4 | R35: 1 | S35: 12 | T35: 24 | U35: 182661.6 | V35: 365323.2
A36: 34 | C36: MRS. B.S. ODEMAKINDE | D36: 500000 | E36: =D36*0.1333 -> 66650 | F36: =G36*H36 -> 708312.5 | G36: 50 | H36: 14166.25 | I36: =E36/G36 -> 1333 | J36: =D36/G36 -> 10000 | K36: =M36*I36 -> 29326 | L36: =I36*N36 -> 37324 | M36: =S36+R36 -> 22 | N36: =T36-R36 -> 28 | O36: =U36+H36 -> 252159.25 | P36: =V36-H36 -> 314490.75 | R36: 1 | S36: 21 | T36: 29 | U36: 237993 | V36: 328657
A37: 35 | C37: MR. MARTINS K. O. | D37: 450000 | E37: =D37*0.1333 -> 59985 | F37: =G37*H37 -> 509985 | G37: 50 | H37: 10199.7 | I37: =E37/G37 -> 1199.7 | J37: =D37/G37 -> 9000 | K37: =M37*I37 -> 19195.2 | L37: =I37*N37 -> 40789.8 | M37: =S37+R37 -> 16 | N37: =T37-R37 -> 34 | O37: =U37+H37 -> 173394.9 | P37: =V37-H37 -> 346789.8 | R37: 1 | S37: 15 | T37: 35 | U37: 163195.2 | V37: 356989.5
A38: 36 | B38: 0 | C38: ADEBOYA O. O. | D38: 450000 | E38: =D38*0.1333 -> 59985 | F38: =G38*H38 -> 509985 | G38: 50 | H38: 10199.7 | I38: =E38/G38 -> 1199.7 | J38: =D38/G38 -> 9000 | K38: =M38*I38 -> 34791.3 | L38: =I38*N38 -> 25193.7 | M38: =S38+R38 -> 29 | N38: =T38-R38 -> 21 | O38: =U38+H38 -> 295791.3 | P38: =V38-H38 -> 214193.7 | R38: 1 | S38: 28 | T38: 22 | U38: 285591.6 | V38: 224393.4
A39: 37 | B39: 0 | C39: MRS D.I KOMOLAFE | D39: 450000 | E39: =D39*0.1333 -> 59985 | F39: =G39*H39 -> 566650 | G39: 50 | H39: 11333 | I39: =E39/G39 -> 1199.7 | J39: =D39/G39 -> 9000 | K39: =M39*I39 -> 2399.4 | L39: =I39*N39 -> 58785.3 | M39: =S39+R39 -> 2 | N39: =T39-R39 -> 49 | O39: =U39+H39 -> 22666 | P39: =V39-H39 -> 657314 | R39: 1 | S39: 1 | T39: 50 | U39: 11333 | V39: 668647
A40: 38 | B40: 0 | C40: E. T. OYENIRAN | D40: 330000 | E40: =D40*0.1333 -> 43989 | F40: =G40*H40 -> 373989 | G40: 50 | H40: 7479.78 | I40: =E40/G40 -> 879.78 | J40: =D40/G40 -> 6600 | K40: =M40*I40 -> 879.78 | L40: =I40*N40 -> 43109.22 | M40: 1 | N40: 49 | O40: 7479.78 | P40: =V40-H40 -> 142115.82 | R40: 1 | S40: 1 | T40: 49 | U40: 11333 | V40: 149595.6
A41: 39 | B41: 0 | C41: OLANIYAN O. | D41: 330000 | E41: =D41*0.1333 -> 43989 | F41: =G41*H41 -> 373989 | G41: 50 | H41: 7479.78 | I41: =E41/G41 -> 879.78 | J41: =D41/G41 -> 6600 | K41: =M41*I41 -> 43109.22 | L41: =I41*N41 -> 1759.56 | M41: =S41+R41 -> 49 | N41: =T41-R41 -> 2 | O41: =U41+H41 -> 306670.98 | P41: =V41-H41 -> 0 | R41: 1 | S41: 48 | T41: 3 | U41: 299191.2 | V41: 7479.78
A42: 40 | B42: 0 | C42: MR. L.K. YUSUFF | D42: 450000 | E42: =D42*0.1333 -> 59985 | F42: =G42*H42 -> 509985 | G42: 50 | H42: 10199.7 | I42: =E42/G42 -> 1199.7 | J42: =D42/G42 -> 9000 | K42: =M42*I42 -> 2399.4 | L42: =I42*N42 -> 57585.6 | M42: =S42+R42 -> 2 | N42: =T42-R42 -> 48 | O42: =U42+H42 -> 173394.9 | P42: =V42-H42 -> 489585.6 | R42: 1 | S42: 1 | T42: 49 | U42: 163195.2 | V42: 499785.3 | X42: =SUM(H34:H42) -> 94279.71
A43: 41 | B43: 0 | C43: MRS. A. YUSUFF | D43: 330000 | E43: =D43*0.1333 -> 43989 | F43: =G43*H43 -> 373989 | G43: 50 | H43: 7479.78 | I43: =E43/G43 -> 879.78 | J43: =D43/G43 -> 6600 | K43: =M43*I43 -> 25513.62 | L43: =I43*N43 -> 18475.38 | M43: =S43+R43 -> 29 | N43: =T43-R43 -> 21 | O43: =U43+H43 -> 216913.62 | P43: =V43-H43 -> 157075.38 | R43: 1 | S43: 28 | T43: 22 | U43: 209433.84 | V43: 164555.16 | X43: =SUM(H43:H43) -> 7479.78 | Z43: LAW/REPORT
A44: 42 | B44: 0 | C44: MRS R.A. KOLAWOLE | D44: 500000 | E44: =D44*0.1333 -> 66650 | F44: =G44*H44 -> 424987.5 | G44: 50 | H44: 8499.75 | I44: =E44/G44 -> 1333 | J44: =D44/G44 -> 10000 | K44: =M44*I44 -> 2666 | L44: =I44*N44 -> 65317 | M44: =S44+R44 -> 2 | N44: =T44-R44 -> 49 | O44: =U44+H44 -> 16999.5 | P44: =V44-H44 -> 492985.5 | R44: 1 | S44: 1 | T44: 50 | U44: 8499.75 | V44: 501485.25
A45: 43 | B45: 0 | C45: MR. A. ESAN | D45: 330000 | E45: =D45*0.1333 -> 43989 | F45: =G45*H45 -> 373989 | G45: 50 | H45: 7479.78 | I45: =E45/G45 -> 879.78 | J45: =D45/G45 -> 6600 | K45: =M45*I45 -> 21994.5 | L45: =I45*N45 -> 21994.5 | M45: =S45+R45 -> 25 | N45: =T45-R45 -> 25 | O45: =U45+H45 -> 186994.5 | P45: =V45-H45 -> 186994.5 | R45: 1 | S45: 24 | T45: 26 | U45: 179514.72 | V45: 194474.28 | X45: =SUM(H44:H45) -> 15979.53 | Z45: LIBRRARY
A46: 44 | B46: 0 | C46: ELEGBEDE CHRISTIANAH | D46: 450000 | E46: =D46*0.1333 -> 59985 | F46: =G46*H46 -> 0 | G46: 50 | H46: 0 | I46: =E46/G46 -> 1199.7 | J46: =D46/G46 -> 9000 | K46: =M46*I46 -> 61184.7 | L46: =I46*N46 -> 0 | M46: =S46+R46 -> 51 | N46: =T46-R46 -> 0 | O46: =U46+H46 -> 438587.1 | P46: =V46-H46 -> 71397.9 | R46: 1 | S46: 50 | T46: 1 | U46: 438587.1 | V46: 71397.9 | Z46: LIT A
A47: 45 | B47: 0 | C47: A. FALADE | D47: 450000 | E47: =D47*0.1333 -> 59985 | F47: =G47*H47 -> 509985 | G47: 50 | H47: 10199.7 | I47: =E47/G47 -> 1199.7 | J47: =D47/G47 -> 9000 | K47: =M47*I47 -> 35991 | L47: =I47*N47 -> 23994 | M47: =S47+R47 -> 30 | N47: =T47-R47 -> 20 | O47: =U47+H47 -> 305991 | P47: =V47-H47 -> 193794.3 | R47: 1 | S47: 29 | T47: 21 | U47: 295791.3 | V47: 203994
A48: 46 | B48: 0 | C48: AKINPELU ABIODUN | D48: 450000 | E48: =D48*0.1333 -> 59985 | F48: =G48*H48 -> 0 | G48: 50 | H48: 0 | I48: =E48/G48 -> 1199.7 | J48: =D48/G48 -> 9000 | K48: =M48*I48 -> 61184.7 | L48: =I48*N48 -> 0 | M48: =S48+R48 -> 51 | N48: =T48-R48 -> 0 | O48: =U48+H48 -> 438587.1 | P48: =V48-H48 -> 71397.9 | R48: 1 | S48: 50 | T48: 1 | U48: 438587.1 | V48: 71397.9
A49: 47 | B49: 0 | C49: MRS. A. T. TIJANI | D49: 330000 | E49: =D49*0.1333 -> 43989 | F49: =G49*H49 -> 373989 | G49: 50 | H49: 7479.78 | I49: =E49/G49 -> 879.78 | J49: =D49/G49 -> 6600 | K49: =M49*I49 -> 23754.06 | L49: =I49*N49 -> 20234.94 | M49: =S49+R49 -> 27 | N49: =T49-R49 -> 23 | O49: =U49+H49 -> 201954.06 | P49: =V49-H49 -> 179514.72 | R49: 1 | S49: 26 | T49: 24 | U49: 194474.28 | V49: 186994.5
A50: 48 | B50: 0 | C50: MR. S. T. AMOO | D50: 450000 | E50: =D50*0.1333 -> 59985 | F50: =G50*H50 -> 509985 | G50: 50 | H50: 10199.7 | I50: =E50/G50 -> 1199.7 | J50: =D50/G50 -> 9000 | K50: =M50*I50 -> 19195.2 | L50: =I50*N50 -> 40789.8 | M50: =S50+R50 -> 16 | N50: =T50-R50 -> 34 | O50: =U50+H50 -> 173394.9 | P50: =V50-H50 -> 346789.8 | R50: 1 | S50: 15 | T50: 35 | U50: 163195.2 | V50: 356989.5
A51: 49 | B51: 0 | C51: MR. A. D. AYOADE | D51: 500000 | E51: =D51*0.1333 -> 66650 | F51: =G51*H51 -> 566650 | G51: 50 | H51: 11333 | I51: =E51/G51 -> 1333 | J51: =D51/G51 -> 10000 | K51: =M51*I51 -> 13330 | L51: =I51*N51 -> 53320 | M51: =S51+R51 -> 10 | N51: =T51-R51 -> 40 | O51: =U51+H51 -> 113330 | P51: =V51-H51 -> 453320 | R51: 1 | S51: 9 | T51: 41 | U51: 101997 | V51: 464653 | X51: =SUM(H46:H52) -> 52545.18
A52: 50 | B52: 0 | C52: MR A.A. SODEINDE | D52: 450001 | E52: =D52*0.1333 -> 59985.133 | F52: =G52*H52 -> 666650 | G52: 50 | H52: 13333 | I52: =E52/G52 -> 1199.7027 | J52: =D52/G52 -> 9000.02 | K52: =M52*I52 -> 19195.243 | L52: =I52*N52 -> 40789.891 | M52: =S52+R52 -> 16 | N52: =T52-R52 -> 34 | O52: =U52+H52 -> 176528.2 | P52: =V52-H52 -> 343656.5 | R52: 1 | S52: 15 | T52: 35 | U52: 163195.2 | V52: 356989.5
A53: 51 | B53: 0 | C53: LAWAL F. A. | D53: 330000 | E53: =D53*0.1333 -> 43989 | F53: =G53*H53 -> 373989 | G53: 50 | H53: 7479.78 | I53: =E53/G53 -> 879.78 | J53: =D53/G53 -> 6600 | K53: =M53*I53 -> 20234.94 | L53: =I53*N53 -> 23754.06 | M53: =S53+R53 -> 23 | N53: =T53-R53 -> 27 | O53: =U53+H53 -> 172034.94 | P53: =V53-H53 -> 201954.06 | R53: 1 | S53: 22 | T53: 28 | U53: 164555.16 | V53: 209433.84 | Z53: LIT B
A54: 52 | B54: 0 | C54: SAFIU-OLALERE S, K | D54: 330000 | E54: =D54*0.1333 -> 43989 | F54: =G54*H54 -> 373989 | G54: 50 | H54: 7479.78 | I54: =E54/G54 -> 879.78 | J54: =D54/G54 -> 6600 | K54: =M54*I54 -> 25513.62 | L54: =I54*N54 -> 18475.38 | M54: =S54+R54 -> 29 | N54: =T54-R54 -> 21 | O54: =U54+H54 -> 216913.62 | P54: =V54-H54 -> 157075.38 | R54: 1 | S54: 28 | T54: 22 | U54: 209433.84 | V54: 164555.16
A55: 53 | B55: 0 | C55: MR A.A.ADUNMADEHIN | D55: 500000 | E55: =D55*0.1333 -> 66650 | F55: =G55*H55 -> 424987.5 | G55: 50 | H55: 8499.75 | I55: =E55/G55 -> 1333 | J55: =D55/G55 -> 10000 | K55: =M55*I55 -> 2666 | L55: =I55*N55 -> 65317 | M55: =S55+R55 -> 2 | N55: =T55-R55 -> 49 | O55: =U55+H55 -> 16999.5 | P55: =V55-H55 -> 492985.5 | R55: 1 | S55: 1 | T55: 50 | U55: 8499.75 | V55: 501485.25
A56: 54 | B56: 0 | C56: MR. S. G. OSINEYE | D56: 330000 | E56: =D56*0.1333 -> 43989 | F56: =G56*H56 -> 373989 | G56: 50 | H56: 7479.78 | I56: =E56/G56 -> 879.78 | J56: =D56/G56 -> 6600 | K56: =M56*I56 -> 23754.06 | L56: =I56*N56 -> 20234.94 | M56: =S56+R56 -> 27 | N56: =T56-R56 -> 23 | O56: =U56+H56 -> 201954.06 | P56: =V56-H56 -> 172034.94 | R56: 1 | S56: 26 | T56: 24 | U56: 194474.28 | V56: 179514.72
A57: 55 | B57: 0 | C57: TIJANI S. D. | D57: 330000 | E57: =D57*0.1333 -> 43989 | F57: =G57*H57 -> 273993 | G57: 50 | H57: 5479.86 | I57: =E57/G57 -> 879.78 | J57: =D57/G57 -> 6600 | K57: =M57*I57 -> 43989 | L57: =I57*N57 -> 879.78 | M57: =S57+R57 -> 50 | N57: =T57-R57 -> 1 | O57: =U57+H57 -> 319630.62 | P57: =V57-H57 -> 66797.72 | R57: 1 | S57: 49 | T57: 2 | U57: 314150.76 | V57: 72277.58
A58: 56 | C58: MR. A. T. BAKARE | D58: 450000 | E58: =D58*0.1333 -> 59985 | F58: =G58*H58 -> 509985 | G58: 50 | H58: 10199.7 | I58: =E58/G58 -> 1199.7 | J58: =D58/G58 -> 9000 | K58: =M58*I58 -> 4798.8 | L58: =I58*N58 -> 55186.2 | M58: =S58+R58 -> 4 | N58: =T58-R58 -> 46 | O58: =U58+H58 -> 40798.8 | P58: =V58-H58 -> 448786.8 | R58: 1 | S58: 3 | T58: 47 | U58: 30599.1 | V58: 458986.5
A59: 57 | B59: 0 | C59: MR. O. O. ALAO | D59: 330000 | E59: =D59*0.1333 -> 43989 | F59: =G59*H59 -> 373989 | G59: 50 | H59: 7479.78 | I59: =E59/G59 -> 879.78 | J59: =D59/G59 -> 6600 | K59: =M59*I59 -> 34311.42 | L59: =I59*N59 -> 10557.36 | M59: =S59+R59 -> 39 | N59: =T59-R59 -> 12 | O59: =U59+H59 -> 284231.64 | P59: =V59-H59 -> 89757.36 | R59: 1 | S59: 38 | T59: 13 | U59: 276751.86 | V59: 97237.14 | X59: =SUM(H53:H61) -> 80497.83
A60: 58 | C60: MISS A.D. ADEOYE | D60: 450000 | E60: =D60*0.1333 -> 59985 | F60: =G60*H60 -> 809985 | G60: 50 | H60: 16199.7 | I60: =E60/G60 -> 1199.7 | J60: =D60/G60 -> 9000 | K60: =M60*I60 -> 2399.4 | L60: =I60*N60 -> 57585.6 | M60: =S60+R60 -> 2 | N60: =T60-R60 -> 48 | O60: =U60+H60 -> 32399.4 | P60: =V60-H60 -> 453591.6 | R60: 1 | S60: 1 | T60: 49 | U60: 16199.7 | V60: 469791.3
A61: 59 | C61: MR O.E ODUNTAN | D61: 450000 | E61: =D61*0.1333 -> 59985 | F61: =G61*H61 -> 509985 | G61: 50 | H61: 10199.7 | I61: =E61/G61 -> 1199.7 | J61: =D61/G61 -> 9000 | K61: =M61*I61 -> 2399.4 | L61: =I61*N61 -> 57585.6 | M61: =S61+R61 -> 2 | N61: =T61-R61 -> 48 | O61: =U61+H61 -> 20399.4 | P61: =V61-H61 -> 489585.6 | R61: 1 | S61: 1 | T61: 49 | U61: 10199.7 | V61: 499785.3
A62: 60 | B62: 0 | C62: ADEYEMO G. | D62: 330000 | E62: =D62*0.1333 -> 43989 | F62: =G62*H62 -> 373989 | G62: 50 | H62: 7479.78 | I62: =E62/G62 -> 879.78 | J62: =D62/G62 -> 6600 | K62: =M62*I62 -> 33431.64 | L62: =I62*N62 -> 11437.14 | M62: =S62+R62 -> 38 | N62: =T62-R62 -> 13 | O62: =U62+H62 -> 276751.86 | P62: =V62-H62 -> 97237.14 | R62: 1 | S62: 37 | T62: 14 | U62: 269272.08 | V62: 104716.92 | Z62: LIT C
A63: 61 | B63: 0 | C63: AJALA O. | D63: 330000 | E63: =D63*0.1333 -> 43989 | F63: =G63*H63 -> 373989 | G63: 50 | H63: 7479.78 | I63: =E63/G63 -> 879.78 | J63: =D63/G63 -> 6600 | K63: =M63*I63 -> 20234.94 | L63: =I63*N63 -> 23754.06 | M63: =S63+R63 -> 23 | N63: =T63-R63 -> 27 | O63: =U63+H63 -> 172034.94 | P63: =V63-H63 -> 201954.06 | R63: 1 | S63: 22 | T63: 28 | U63: 164555.16 | V63: 209433.84
A64: 62 | B64: 0 | C64: MR. A. L.AWE | D64: 450000 | E64: =D64*0.1333 -> 59985 | F64: =G64*H64 -> 502322 | G64: 50 | H64: 10046.44 | I64: =E64/G64 -> 1199.7 | J64: =D64/G64 -> 9000 | K64: =M64*I64 -> 32391.9 | L64: =I64*N64 -> 27593.1 | M64: =S64+R64 -> 27 | N64: =T64-R64 -> 23 | O64: =U64+H64 -> 271253.88 | P64: =V64-H64 -> 231068.12 | R64: 1 | S64: 26 | T64: 24 | U64: 261207.44 | V64: 241114.56
A65: 63 | B65: 0 | C65: FAGBAYIMU A. G. | D65: 330000 | E65: =D65*0.1333 -> 43989 | F65: =G65*H65 -> 373989 | G65: 50 | H65: 7479.78 | I65: =E65/G65 -> 879.78 | J65: =D65/G65 -> 6600 | K65: =M65*I65 -> 20234.94 | L65: =I65*N65 -> 23754.06 | M65: =S65+R65 -> 23 | N65: =T65-R65 -> 27 | O65: =U65+H65 -> 172034.94 | P65: =V65-H65 -> 201954.06 | R65: 1 | S65: 22 | T65: 28 | U65: 164555.16 | V65: 209433.84 | X65: =SUM(H62:H65) -> 32485.78
A66: 64 | B66: 0 | C66: O. O. SUNMONU | D66: 330000 | E66: =D66*0.1333 -> 43989 | F66: =G66*H66 -> 373989 | G66: 50 | H66: 7479.78 | I66: =E66/G66 -> 879.78 | J66: =D66/G66 -> 6600 | K66: =M66*I66 -> 26393.4 | L66: =I66*N66 -> 17595.6 | M66: =S66+R66 -> 30 | N66: =T66-R66 -> 20 | O66: =U66+H66 -> 224393.4 | P66: =V66-H66 -> 149595.6 | R66: 1 | S66: 29 | T66: 21 | U66: 216913.62 | V66: 157075.38
A67: 65 | B67: 0 | C67: OWOADE OBEMBE. S. | D67: 330000 | E67: =D67*0.1333 -> 43989 | F67: =G67*H67 -> 373989 | G67: 50 | H67: 7479.78 | I67: =E67/G67 -> 879.78 | J67: =D67/G67 -> 6600 | K67: =M67*I67 -> 33431.64 | L67: =I67*N67 -> 11437.14 | M67: =S67+R67 -> 38 | N67: =T67-R67 -> 13 | O67: =U67+H67 -> 276754.26 | P67: =V67-H67 -> 97234.74 | R67: 1 | S67: 37 | T67: 14 | U67: 269274.48 | V67: 104714.52
A68: 66 | B68: 0 | C68: LADEOKIN M. A. | D68: 330000 | E68: =D68*0.1333 -> 43989 | F68: =G68*H68 -> 373989 | G68: 50 | H68: 7479.78 | I68: =E68/G68 -> 879.78 | J68: =D68/G68 -> 6600 | K68: =M68*I68 -> 43989 | L68: =I68*N68 -> 879.78 | M68: =S68+R68 -> 50 | N68: =T68-R68 -> 1 | O68: =U68+H68 -> 321630.54 | P68: =V68-H68 -> 52358.46 | R68: 1 | S68: 49 | T68: 2 | U68: 314150.76 | V68: 59838.24 | Z68: LIT D
A69: 67 | C69: MRS. V. O. ADEYEMI | D69: 330000 | E69: =D69*0.1333 -> 43989 | F69: =G69*H69 -> 373989 | G69: 50 | H69: 7479.78 | I69: =E69/G69 -> 879.78 | J69: =D69/G69 -> 6600 | K69: =M69*I69 -> 11437.14 | L69: =I69*N69 -> 32551.86 | M69: =S69+R69 -> 13 | N69: =T69-R69 -> 37 | O69: =U69+H69 -> 97237.14 | P69: =V69-H69 -> 276751.86 | R69: 1 | S69: 12 | T69: 38 | U69: 89757.36 | V69: 284231.64
A70: 68 | B70: 0 | C70: MRS K.O OKIN | D70: 500000 | E70: =D70*0.1333 -> 66650 | F70: =G70*H70 -> 424987.5 | G70: 50 | H70: 8499.75 | I70: =E70/G70 -> 1333 | J70: =D70/G70 -> 10000 | K70: =M70*I70 -> 2666 | L70: =I70*N70 -> 65317 | M70: =S70+R70 -> 2 | N70: =T70-R70 -> 49 | O70: =U70+H70 -> 16999.5 | P70: =V70-H70 -> 492985.5 | R70: 1 | S70: 1 | T70: 50 | U70: 8499.75 | V70: 501485.25
A71: 69 | B71: 0 | C71: MRS. B. F. ADEYEMI | D71: 330000 | E71: =D71*0.1333 -> 43989 | F71: =G71*H71 -> 373989 | G71: 50 | H71: 7479.78 | I71: =E71/G71 -> 879.78 | J71: =D71/G71 -> 6600 | K71: =M71*I71 -> 35191.2 | L71: =I71*N71 -> 9677.58 | M71: =S71+R71 -> 40 | N71: =T71-R71 -> 11 | O71: =U71+H71 -> 291711.42 | P71: =V71-H71 -> 82277.58 | R71: 1 | S71: 39 | T71: 12 | U71: 284231.64 | V71: 89757.36
A72: 70 | B72: 0 | C72: AYANNIRAN O. | D72: 330000 | E72: =D72*0.1333 -> 43989 | F72: =G72*H72 -> 373989 | G72: 50 | H72: 7479.78 | I72: =E72/G72 -> 879.78 | J72: =D72/G72 -> 6600 | K72: =M72*I72 -> 36070.98 | L72: =I72*N72 -> 8797.8 | M72: =S72+R72 -> 41 | N72: =T72-R72 -> 10 | O72: =U72+H72 -> 299191.2 | P72: =V72-H72 -> 74797.8 | R72: 1 | S72: 40 | T72: 11 | U72: 291711.42 | V72: 82277.58
A73: 71 | B73: 0 | C73: OKULAJA A. F., B. | D73: 330000 | E73: =D73*0.1333 -> 43989 | F73: =G73*H73 -> 373989 | G73: 50 | H73: 7479.78 | I73: =E73/G73 -> 879.78 | J73: =D73/G73 -> 6600 | K73: =M73*I73 -> 43989 | L73: =I73*N73 -> 879.78 | M73: =S73+R73 -> 50 | N73: =T73-R73 -> 1 | O73: =U73+H73 -> 321630.54 | P73: =V73-H73 -> 89757.36 | R73: 1 | S73: 49 | T73: 2 | U73: 314150.76 | V73: 97237.14
A74: 72 | B74: 0 | C74: OLAIYAPO I. B. | D74: 150000 | E74: =D74*0.1333 -> 19995 | F74: =G74*H74 -> 169995 | G74: 50 | H74: 3399.9 | I74: =E74/G74 -> 399.9 | J74: =D74/G74 -> 3000 | K74: =M74*I74 -> 15196.2 | L74: =I74*N74 -> 5198.7 | M74: =S74+R74 -> 38 | N74: =T74-R74 -> 13 | O74: =U74+H74 -> 125796.3 | P74: =V74-H74 -> 44198.7 | R74: 1 | S74: 37 | T74: 14 | U74: 122396.4 | V74: 47598.6
A75: 73 | B75: 0 | C75: MR. J. O. ALAO | D75: 150000 | E75: =D75*0.1333 -> 19995 | F75: =G75*H75 -> 169995 | G75: 50 | H75: 3399.9 | I75: =E75/G75 -> 399.9 | J75: =D75/G75 -> 3000 | K75: =M75*I75 -> 10797.3 | L75: =I75*N75 -> 9197.7 | M75: =S75+R75 -> 27 | N75: =T75-R75 -> 23 | O75: =U75+H75 -> 95197.2 | P75: =V75-H75 -> 78197.7 | R75: 1 | S75: 26 | T75: 24 | U75: 91797.3 | V75: 81597.6
A76: 74 | C76: MR. F. O. OMOTOSHO | D76: 330000 | E76: =D76*0.1333 -> 43989 | F76: =G76*H76 -> 373989 | G76: 50 | H76: 7479.78 | I76: =E76/G76 -> 879.78 | J76: =D76/G76 -> 6600 | K76: =M76*I76 -> 19355.16 | L76: =I76*N76 -> 24633.84 | M76: =S76+R76 -> 22 | N76: =T76-R76 -> 28 | O76: =U76+H76 -> 164555.16 | P76: =V76-H76 -> 209433.84 | R76: 1 | S76: 21 | T76: 29 | U76: 157075.38 | V76: 216913.62
A77: 75 | C77: MRS. F. B. OLAMILETRILLION | D77: 330000 | E77: =D77*0.1333 -> 43989 | F77: =G77*H77 -> 373989 | G77: 50 | H77: 7479.78 | I77: =E77/G77 -> 879.78 | J77: =D77/G77 -> 6600 | K77: =M77*I77 -> 15836.04 | L77: =I77*N77 -> 28152.96 | M77: =S77+R77 -> 18 | N77: =T77-R77 -> 32 | O77: =U77+H77 -> 134636.04 | P77: =V77-H77 -> 239352.96 | R77: 1 | S77: 17 | T77: 33 | U77: 127156.26 | V77: 246832.74
A78: 76 | C78: MR M.O OLAJIDE | D78: 330000 | E78: =D78*0.1333 -> 43989 | F78: =G78*H78 -> 373989 | G78: 50 | H78: 7479.78 | I78: =E78/G78 -> 879.78 | J78: =D78/G78 -> 6600 | K78: =M78*I78 -> 1759.56 | L78: =I78*N78 -> 42229.44 | M78: =S78+R78 -> 2 | N78: =T78-R78 -> 48 | O78: =U78+H78 -> 14959.56 | P78: =V78-H78 -> 359029.44 | R78: 1 | S78: 1 | T78: 49 | U78: 7479.78 | V78: 366509.22
A79: 77 | C79: MRS. A. A. ADEOYE | D79: 330000 | E79: =D79*0.1333 -> 43989 | F79: =G79*H79 -> 373989 | G79: 50 | H79: 7479.78 | I79: =E79/G79 -> 879.78 | J79: =D79/G79 -> 6600 | K79: =M79*I79 -> 15836.04 | L79: =I79*N79 -> 28152.96 | M79: =S79+R79 -> 18 | N79: =T79-R79 -> 32 | O79: =U79+H79 -> 134636.04 | P79: =V79-H79 -> 239352.96 | R79: 1 | S79: 17 | T79: 33 | U79: 127156.26 | V79: 246832.74
A80: 78 | C80: MRS. OLUWASOGO FATUNBI | D80: 150000 | E80: =D80*0.1333 -> 19995 | F80: =G80*H80 -> 169995 | G80: 50 | H80: 3399.9 | I80: =E80/G80 -> 399.9 | J80: =D80/G80 -> 3000 | K80: =M80*I80 -> 1999.5 | L80: =I80*N80 -> 17995.5 | M80: =S80+R80 -> 5 | N80: =T80-R80 -> 45 | O80: =U80+H80 -> 16999.5 | P80: =V80-H80 -> 152995.5 | R80: 1 | S80: 4 | T80: 46 | U80: 13599.6 | V80: 156395.4 | X80: =SUM(H66:H80) -> 100977.03
A81: 79 | C81: MRS. E. M. ABEGUNDE | D81: 450000 | E81: =D81*0.1333 -> 59985 | F81: =G81*H81 -> 509995 | G81: 50 | H81: 10199.9 | I81: =E81/G81 -> 1199.7 | J81: =D81/G81 -> 9000 | K81: =M81*I81 -> 16795.8 | L81: =I81*N81 -> 43189.2 | M81: =S81+R81 -> 14 | N81: =T81-R81 -> 36 | O81: =U81+H81 -> 142798.6 | P81: =V81-H81 -> 367196.4 | R81: 1 | S81: 13 | T81: 37 | U81: 132598.7 | V81: 377396.3 | Z81: LIT E
A82: 80 | B82: 0 | C82: OYEJIDE F. O. | D82: 450000 | E82: =D82*0.1333 -> 59985 | F82: =G82*H82 -> 509494.5 | G82: 50 | H82: 10189.89 | I82: =E82/G82 -> 1199.7 | J82: =D82/G82 -> 9000 | K82: =M82*I82 -> 61184.7 | L82: =I82*N82 -> 0 | M82: =S82+R82 -> 51 | N82: =T82-R82 -> 0 | O82: =U82+H82 -> 438595.49 | P82: =V82-H82 -> 71399.51 | R82: 1 | S82: 50 | T82: 1 | U82: 428405.6 | V82: 81589.4
A83: 81 | B83: 0 | C83: MRS. M. O. AYOADE | D83: 330000 | E83: =D83*0.1333 -> 43989 | F83: =G83*H83 -> 373989 | G83: 50 | H83: 7479.78 | I83: =E83/G83 -> 879.78 | J83: =D83/G83 -> 6600 | K83: =M83*I83 -> 23754.06 | L83: =I83*N83 -> 20234.94 | M83: =S83+R83 -> 27 | N83: =T83-R83 -> 23 | O83: =U83+H83 -> 201954.06 | P83: =V83-H83 -> 172034.94 | R83: 1 | S83: 26 | T83: 24 | U83: 194474.28 | V83: 179514.72
A84: 82 | C84: MRS. O. B. AYOOLA | D84: 330000 | E84: =D84*0.1333 -> 43989 | F84: =G84*H84 -> 356393.4 | G84: 30 | H84: 11879.78 | I84: =E84/G84 -> 1466.3 | J84: =D84/G84 -> 11000 | K84: =M84*I84 -> 23460.8 | L84: =I84*N84 -> 20528.2 | M84: =S84+R84 -> 16 | N84: =T84-R84 -> 14 | O84: =U84+H84 -> 190076.48 | P84: =V84-H84 -> 166316.92 | R84: 1 | S84: 15 | T84: 15 | U84: 178196.7 | V84: 178196.7
A85: 83 | C85: MRS. E. O. OMOJUWA | D85: 330000 | E85: =D85*0.1333 -> 43989 | F85: =G85*H85 -> 351114.72 | G85: 24 | H85: 14629.78 | I85: =E85/G85 -> 1832.875 | J85: =D85/G85 -> 13750 | K85: =M85*I85 -> 27493.125 | L85: =I85*N85 -> 64150.625 | M85: =S85+R85 -> 15 | N85: =T85-R85 -> 35 | O85: =U85+H85 -> 219446.7 | P85: =V85-H85 -> 131668.02 | R85: 1 | S85: 14 | T85: 36 | U85: 204816.92 | V85: 146297.8
A86: 84 | C86: MR. S. AWE | D86: 150000 | E86: =D86*0.1333 -> 19995 | F86: =G86*H86 -> 169995 | G86: 50 | H86: 3399.9 | I86: =E86/G86 -> 399.9 | J86: =D86/G86 -> 3000 | K86: =M86*I86 -> 2799.3 | L86: =I86*N86 -> 17195.7 | M86: =S86+R86 -> 7 | N86: =T86-R86 -> 43 | O86: =U86+H86 -> 23799.3 | P86: =V86-H86 -> 146195.7 | R86: 1 | S86: 6 | T86: 44 | U86: 20399.4 | V86: 149595.6
A87: 85 | C87: MRS. R. T. LAWAL | D87: 350000 | E87: =D87*0.1333 -> 46655 | F87: =G87*H87 -> 373989 | G87: 50 | H87: 7479.78 | I87: =E87/G87 -> 933.1 | J87: =D87/G87 -> 7000 | K87: =M87*I87 -> 2799.3 | L87: =I87*N87 -> 43855.7 | M87: =S87+R87 -> 3 | N87: =T87-R87 -> 47 | O87: =U87+H87 -> 22439.34 | P87: =V87-H87 -> 351549.66 | R87: 1 | S87: 2 | T87: 48 | U87: 14959.56 | V87: 359029.44 | X87: =SUM(H81:H87) -> 65258.81
A88: 86 | B88: 0 | C88: ADAMS TAIWO | D88: 150000 | E88: =D88*0.1333 -> 19995 | F88: =G88*H88 -> 169995 | G88: 50 | H88: 3399.9 | I88: =E88/G88 -> 399.9 | J88: =D88/G88 -> 3000 | K88: =M88*I88 -> 14796.3 | L88: =I88*N88 -> 5598.6 | M88: =S88+R88 -> 37 | N88: =T88-R88 -> 14 | O88: =U88+H88 -> 125796.3 | P88: =V88-H88 -> 44198.7 | R88: 1 | S88: 36 | T88: 15 | U88: 122396.4 | V88: 47598.6 | Z88: LIT F
A89: 87 | B89: 0 | C89: OBASOOTO O. R | D89: 500000 | E89: =D89*0.1333 -> 66650 | F89: =G89*H89 -> 424987.5 | G89: 50 | H89: 8499.75 | I89: =E89/G89 -> 1333 | J89: =D89/G89 -> 10000 | K89: =M89*I89 -> 2666 | L89: =I89*N89 -> 65317 | M89: =S89+R89 -> 2 | N89: =T89-R89 -> 49 | O89: =U89+H89 -> 16999.5 | P89: =V89-H89 -> 492985.5 | R89: 1 | S89: 1 | T89: 50 | U89: 8499.75 | V89: 501485.25
A90: 88 | B90: 0 | C90: ADEBOLA C.E | D90: 500001 | E90: =D90*0.1333 -> 66650.133 | F90: =G90*H90 -> 424987.5 | G90: 50 | H90: 8499.75 | I90: =E90/G90 -> 1333.0027 | J90: =D90/G90 -> 10000.02 | K90: =M90*I90 -> 2666.0053 | L90: =I90*N90 -> 65317.131 | M90: =S90+R90 -> 2 | N90: =T90-R90 -> 49 | O90: =U90+H90 -> 16999.5 | P90: =V90-H90 -> 492985.5 | R90: 1 | S90: 1 | T90: 50 | U90: 8499.75 | V90: 501485.25
A91: 89 | B91: 0 | C91: E. O. HASSAN | D91: 150000 | E91: =D91*0.1333 -> 19995 | F91: =G91*H91 -> 169995 | G91: 50 | H91: 3399.9 | I91: =E91/G91 -> 399.9 | J91: =D91/G91 -> 3000 | K91: =M91*I91 -> 11997 | L91: =I91*N91 -> 7998 | M91: =S91+R91 -> 30 | N91: =T91-R91 -> 20 | O91: =U91+H91 -> 101997 | P91: =V91-H91 -> 67998 | R91: 1 | S91: 29 | T91: 21 | U91: 98597.1 | V91: 71397.9
A92: 90 | B92: 0 | C92: O. A. ASOLO | D92: 150000 | E92: =D92*0.1333 -> 19995 | F92: =G92*H92 -> 169995 | G92: 50 | H92: 3399.9 | I92: =E92/G92 -> 399.9 | J92: =D92/G92 -> 3000 | K92: =M92*I92 -> 11997 | L92: =I92*N92 -> 7998 | M92: =S92+R92 -> 30 | N92: =T92-R92 -> 20 | O92: =U92+H92 -> 101997 | P92: =V92-H92 -> 67998 | R92: 1 | S92: 29 | T92: 21 | U92: 98597.1 | V92: 71397.9
A93: 91 | B93: 0 | C93: MRS. OLUGBADE OYEKALE | D93: 150000 | E93: =D93*0.1333 -> 19995 | F93: =G93*H93 -> 169995 | G93: 50 | H93: 3399.9 | I93: =E93/G93 -> 399.9 | J93: =D93/G93 -> 3000 | K93: =M93*I93 -> 6398.4 | L93: =I93*N93 -> 13596.6 | M93: =S93+R93 -> 16 | N93: =T93-R93 -> 34 | O93: =U93+H93 -> 54398.4 | P93: =V93-H93 -> 115596.6 | R93: 1 | S93: 15 | T93: 35 | U93: 50998.5 | V93: 118996.5
A94: 92 | B94: 0 | C94: MISS. T. OMOTOSHO | D94: 150000 | E94: =D94*0.1333 -> 19995 | F94: =G94*H94 -> 169995 | G94: 50 | H94: 3399.9 | I94: =E94/G94 -> 399.9 | J94: =D94/G94 -> 3000 | K94: =M94*I94 -> 5198.7 | L94: =I94*N94 -> 14796.3 | M94: =S94+R94 -> 13 | N94: =T94-R94 -> 37 | O94: =U94+H94 -> 44198.7 | P94: =V94-H94 -> 125796.3 | R94: 1 | S94: 12 | T94: 38 | U94: 40798.8 | V94: 129196.2
A95: 93 | B95: 0 | C95: MRS. ODUYELU | D95: 150000 | E95: =D95*0.1333 -> 19995 | F95: =G95*H95 -> 169995 | G95: 50 | H95: 3399.9 | I95: =E95/G95 -> 399.9 | J95: =D95/G95 -> 3000 | K95: =M95*I95 -> 4398.9 | L95: =I95*N95 -> 15596.1 | M95: =S95+R95 -> 11 | N95: =T95-R95 -> 39 | O95: =U95+H95 -> 37398.9 | P95: =V95-H95 -> 132596.1 | R95: 1 | S95: 10 | T95: 40 | U95: 33999 | V95: 135996
A96: 94 | B96: 0 | C96: MRS B.O. ADESIDA | D96: 150001 | E96: =D96*0.1333 -> 19995.133 | F96: =G96*H96 -> 169995 | G96: 50 | H96: 3399.9 | I96: =E96/G96 -> 399.90267 | J96: =D96/G96 -> 3000.02 | K96: =M96*I96 -> 4398.9293 | L96: =I96*N96 -> 15596.204 | M96: =S96+R96 -> 11 | N96: =T96-R96 -> 39 | O96: =U96+H96 -> 37398.9 | P96: =V96-H96 -> 132596.1 | R96: 1 | S96: 10 | T96: 40 | U96: 33999 | V96: 135996
A97: 95 | C97: MR. ADETOYE ADEDOKUN | D97: 450000 | E97: =D97*0.1333 -> 59985 | F97: =G97*H97 -> 509985 | G97: 50 | H97: 10199.7 | I97: =E97/G97 -> 1199.7 | J97: =D97/G97 -> 9000 | K97: =M97*I97 -> 10797.3 | L97: =I97*N97 -> 49187.7 | M97: =S97+R97 -> 9 | N97: =T97-R97 -> 41 | O97: =U97+H97 -> 91797.3 | P97: =V97-H97 -> 418187.7 | R97: 1 | S97: 8 | T97: 42 | U97: 81597.6 | V97: 428387.4
A98: 96 | C98: MR. F. TAIWO | D98: 150000 | E98: =D98*0.1333 -> 19995 | F98: =G98*H98 -> 169995 | G98: 50 | H98: 3399.9 | I98: =E98/G98 -> 399.9 | J98: =D98/G98 -> 3000 | K98: =M98*I98 -> 1999.5 | L98: =I98*N98 -> 17995.5 | M98: =S98+R98 -> 5 | N98: =T98-R98 -> 45 | O98: =U98+H98 -> 16999.5 | P98: =V98-H98 -> 152995.5 | R98: 1 | S98: 4 | T98: 46 | U98: 13599.6 | V98: 156395.4 | X98: =SUM(H88:H98) -> 54398.4
A99: 97 | B99: 0 | C99: OLABAMIJI ADETUTU | D99: 330000 | E99: =D99*0.1333 -> 43989 | F99: =G99*H99 -> 373989 | G99: 50 | H99: 7479.78 | I99: =E99/G99 -> 879.78 | J99: =D99/G99 -> 6600 | K99: =M99*I99 -> 20234.94 | L99: =I99*N99 -> 23754.06 | M99: =S99+R99 -> 23 | N99: =T99-R99 -> 27 | O99: =U99+H99 -> 172034.94 | P99: =V99-H99 -> 201954.06 | Q99: * | R99: 1 | S99: 22 | T99: 28 | U99: 164555.16 | V99: 209433.84 | Z99: LIT G
A100: 98 | B100: 0 | C100: MR. O. OSUNLANA | D100: 330000 | E100: =D100*0.1333 -> 43989 | F100: =G100*H100 -> 373989 | G100: 50 | H100: 7479.78 | I100: =E100/G100 -> 879.78 | J100: =D100/G100 -> 6600 | K100: =M100*I100 -> 26393.4 | L100: =I100*N100 -> 17595.6 | M100: =S100+R100 -> 30 | N100: =T100-R100 -> 20 | O100: =U100+H100 -> 216913.62 | P100: =V100-H100 -> 157075.38 | R100: 1 | S100: 29 | T100: 21 | U100: 209433.84 | V100: 164555.16
...

Sheet Sheet2
A1: =Sheet1!A1 -> MDA'S MOTOR-VEHICLE DEDUCTION RETURNS AS AT APRIL, 2020.
A2: =Sheet1!A2 -> S/N | B2: =Sheet1!B2 -> REF. I.D | C2: =Sheet1!C2 -> STAFF NAME | D2: =Sheet1!D2 -> PRINCIPAL N | E2: =Sheet1!E2 -> INTEREST N | F2: =Sheet1!F2 -> TOTAL LOAN N | G2: =Sheet1!G2 -> NO. OF. INSTL. | H2: =Sheet1!H2 -> MONTHLY DED N | ... Q2: =Sheet1!Q2 -> REMARK
A3: =Sheet1!A3 -> 1 | B3: =Sheet1!B3 -> 0 | C3: =Sheet1!C47 -> A. FALADE | D3: =Sheet1!D47 -> 450000 | E3: =Sheet1!E47 -> 59985 | F3: =Sheet1!F47 -> 509985 | G3: =Sheet1!G47 -> 50 | H3: =Sheet1!H47 -> 10199.7 | I3: =Sheet1!I47 -> 1199.7 | J3: =Sheet1!J47 -> 9000 | ... Q3: =Sheet1!Q47 -> 0
A4: =Sheet1!A4 -> 2 | B4: =Sheet1!B4 -> 0 | C4: =Sheet1!C88 -> ADAMS TAIWO | D4: =Sheet1!D88 -> 150000 | E4: =Sheet1!E88 -> 19995 | F4: =Sheet1!F88 -> 169995 | G4: =Sheet1!G88 -> 50 | H4: =Sheet1!H88 -> 3399.9 | I4: =Sheet1!I88 -> 399.9 | J4: =Sheet1!J88 -> 3000 | ... Q4: =Sheet1!Q88 -> 0
A5: =Sheet1!A5 -> 3 | B5: =Sheet1!B5 -> 0 | C5: =Sheet1!C90 -> ADEBOLA C.E | D5: =Sheet1!D90 -> 500001 | E5: =Sheet1!E90 -> 66650.133 | F5: =Sheet1!F90 -> 424987.5 | G5: =Sheet1!G90 -> 50 | H5: =Sheet1!H90 -> 8499.75 | I5: =Sheet1!I90 -> 1333.0027 | J5: =Sheet1!J90 -> 10000.02 | ... Q5: =Sheet1!Q90 -> 0
A6: =Sheet1!A6 -> 4 | B6: =Sheet1!B6 -> 0 | C6: =Sheet1!C38 -> ADEBOYA O. O. | D6: =Sheet1!D38 -> 450000 | E6: =Sheet1!E38 -> 59985 | F6: =Sheet1!F38 -> 509985 | G6: =Sheet1!G38 -> 50 | H6: =Sheet1!H38 -> 10199.7 | I6: =Sheet1!I38 -> 1199.7 | J6: =Sheet1!J38 -> 9000 | ... Q6: =Sheet1!Q38 -> 0
A7: =Sheet1!A7 -> 5 | B7: =Sheet1!B7 -> 0 | C7: =Sheet1!C131 -> ADEDEJI YISAU | D7: =Sheet1!D131 -> 150000 | E7: =Sheet1!E131 -> 19995 | F7: =Sheet1!F131 -> 169995 | G7: =Sheet1!G131 -> 50 | H7: =Sheet1!H131 -> 3399.9 | I7: =Sheet1!I131 -> 399.9 | J7: =Sheet1!J131 -> 3000 | ... Q7: =Sheet1!Q131 -> 0
A8: =Sheet1!A8 -> 6 | B8: =Sheet1!B8 -> 0 | C8: =Sheet1!C4 -> ADENUGA JUMOKE A. | D8: =Sheet1!D4 -> 600000 | E8: =Sheet1!E4 -> 79980 | F8: =Sheet1!F4 -> 679980 | G8: =Sheet1!G4 -> 50 | H8: =Sheet1!H4 -> 13333 | I8: =Sheet1!I4 -> 1599.6 | J8: =Sheet1!J4 -> 12000 | ... Q8: =Sheet1!Q4 -> 0
A9: =Sheet1!A9 -> 7 | B9: =Sheet1!B9 -> 0 | C9: =Sheet1!C112 -> ADERINTO OLADUUNI | D9: =Sheet1!D112 -> 150000 | E9: =Sheet1!E112 -> 19995 | F9: =Sheet1!F112 -> 169995 | G9: =Sheet1!G112 -> 50 | H9: =Sheet1!H112 -> 3399.9 | I9: =Sheet1!I112 -> 399.9 | J9: =Sheet1!J112 -> 3000 | ... Q9: =Sheet1!Q112 -> 0
A10: =Sheet1!A10 -> 8 | B10: =Sheet1!B10 -> 0 | C10: =Sheet1!C62 -> ADEYEMO G. | D10: =Sheet1!D62 -> 330000 | E10: =Sheet1!E62 -> 43989 | F10: =Sheet1!F62 -> 373989 | G10: =Sheet1!G62 -> 50 | H10: =Sheet1!H62 -> 7479.78 | I10: =Sheet1!I62 -> 879.78 | J10: =Sheet1!J62 -> 6600 | ... Q10: =Sheet1!Q62 -> 0
A11: =Sheet1!A11 -> 9 | B11: =Sheet1!B11 -> 0 | C11: =Sheet1!C63 -> AJALA O. | D11: =Sheet1!D63 -> 330000 | E11: =Sheet1!E63 -> 43989 | F11: =Sheet1!F63 -> 373989 | G11: =Sheet1!G63 -> 50 | H11: =Sheet1!H63 -> 7479.78 | I11: =Sheet1!I63 -> 879.78 | J11: =Sheet1!J63 -> 6600 | ... Q11: =Sheet1!Q63 -> 0
A12: =Sheet1!A12 -> 10 | B12: =Sheet1!B12 -> 0 | C12: =Sheet1!C48 -> AKINPELU ABIODUN | D12: =Sheet1!D48 -> 450000 | E12: =Sheet1!E48 -> 59985 | F12: =Sheet1!F48 -> 0 | G12: =Sheet1!G48 -> 50 | H12: =Sheet1!H48 -> 0 | I12: =Sheet1!I48 -> 1199.7 | J12: =Sheet1!J48 -> 9000 | ... Q12: =Sheet1!Q48 -> 0
A13: =Sheet1!A13 -> 11 | B13: =Sheet1!B13 -> 0 | C13: =Sheet1!C34 -> AKINYELE A. A.O. | D13: =Sheet1!D34 -> 500000 | E13: =Sheet1!E34 -> 66650 | F13: =Sheet1!F34 -> 400000 | G13: =Sheet1!G34 -> 50 | H13: =Sheet1!H34 -> 8000 | I13: =Sheet1!I34 -> 1333 | J13: =Sheet1!J34 -> 10000 | ... Q13: =Sheet1!Q34 -> 0
A14: =Sheet1!A14 -> 12 | B14: =Sheet1!B14 -> 0 | C14: =Sheet1!C5 -> ALABI FUNMILAYO S. | D14: =Sheet1!D5 -> 330000 | E14: =Sheet1!E5 -> 43989 | F14: =Sheet1!F5 -> 373989 | G14: =Sheet1!G5 -> 50 | H14: =Sheet1!H5 -> 7479.78 | I14: =Sheet1!I5 -> 879.78 | J14: =Sheet1!J5 -> 6600 | ... Q14: =Sheet1!Q5 -> 0
A15: =Sheet1!A15 -> 13 | B15: =Sheet1!B15 -> 0 | C15: =Sheet1!C124 -> ARANSI MUKAILA | D15: =Sheet1!D124 -> 150000 | E15: =Sheet1!E124 -> 19995 | F15: =Sheet1!F124 -> 169995 | G15: =Sheet1!G124 -> 50 | H15: =Sheet1!H124 -> 3399.9 | I15: =Sheet1!I124 -> 399.9 | J15: =Sheet1!J124 -> 3000 | ... Q15: =Sheet1!Q124 -> 0
A16: =Sheet1!A16 -> 14 | B16: =Sheet1!B16 -> 0 | C16: =Sheet1!C72 -> AYANNIRAN O. | D16: =Sheet1!D72 -> 330000 | E16: =Sheet1!E72 -> 43989 | F16: =Sheet1!F72 -> 373989 | G16: =Sheet1!G72 -> 50 | H16: =Sheet1!H72 -> 7479.78 | I16: =Sheet1!I72 -> 879.78 | J16: =Sheet1!J72 -> 6600 | ... Q16: =Sheet1!Q72 -> 0
A17: =Sheet1!A17 -> 15 | B17: =Sheet1!B17 -> 0 | C17: =Sheet1!C91 -> E. O. HASSAN | D17: =Sheet1!D91 -> 150000 | E17: =Sheet1!E91 -> 19995 | F17: =Sheet1!F91 -> 169995 | G17: =Sheet1!G91 -> 50 | H17: =Sheet1!H91 -> 3399.9 | I17: =Sheet1!I91 -> 399.9 | J17: =Sheet1!J91 -> 3000 | ... Q17: =Sheet1!Q91 -> 0
A18: =Sheet1!A18 -> 16 | B18: =Sheet1!B18 -> 0 | C18: =Sheet1!C40 -> E. T. OYENIRAN | D18: =Sheet1!D40 -> 330000 | E18: =Sheet1!E40 -> 43989 | F18: =Sheet1!F40 -> 373989 | G18: =Sheet1!G40 -> 50 | H18: =Sheet1!H40 -> 7479.78 | I18: =Sheet1!I40 -> 879.78 | J18: =Sheet1!J40 -> 6600 | ... Q18: =Sheet1!Q40 -> 0
A19: =Sheet1!A19 -> 17 | B19: =Sheet1!B19 -> 0 | C19: =Sheet1!C46 -> ELEGBEDE CHRISTIANAH | D19: =Sheet1!D46 -> 450000 | E19: =Sheet1!E46 -> 59985 | F19: =Sheet1!F46 -> 0 | G19: =Sheet1!G46 -> 50 | H19: =Sheet1!H46 -> 0 | I19: =Sheet1!I46 -> 1199.7 | J19: =Sheet1!J46 -> 9000 | ... Q19: =Sheet1!Q46 -> 0
A20: =Sheet1!A20 -> 18 | B20: =Sheet1!B20 -> 0 | C20: =Sheet1!C65 -> FAGBAYIMU A. G. | D20: =Sheet1!D65 -> 330000 | E20: =Sheet1!E65 -> 43989 | F20: =Sheet1!F65 -> 373989 | G20: =Sheet1!G65 -> 50 | H20: =Sheet1!H65 -> 7479.78 | I20: =Sheet1!I65 -> 879.78 | J20: =Sheet1!J65 -> 6600 | ... Q20: =Sheet1!Q65 -> 0
A21: =Sheet1!A21 -> 19 | B21: =Sheet1!B21 -> 0 | C21: =Sheet1!C26 -> FAMOKUN M.O. | D21: =Sheet1!D26 -> 500000 | E21: =Sheet1!E26 -> 66650 | F21: =Sheet1!F26 -> 509985 | G21: =Sheet1!G26 -> 50 | H21: =Sheet1!H26 -> 10199.7 | I21: =Sheet1!I26 -> 1333 | J21: =Sheet1!J26 -> 10000 | ... Q21: =Sheet1!Q26 -> 0
A22: =Sheet1!A22 -> 20 | B22: =Sheet1!B22 -> 0 | C22: =Sheet1!C68 -> LADEOKIN M. A. | D22: =Sheet1!D68 -> 330000 | E22: =Sheet1!E68 -> 43989 | F22: =Sheet1!F68 -> 373989 | G22: =Sheet1!G68 -> 50 | H22: =Sheet1!H68 -> 7479.78 | I22: =Sheet1!I68 -> 879.78 | J22: =Sheet1!J68 -> 6600 | ... Q22: =Sheet1!Q68 -> 0
A23: =Sheet1!A23 -> 21 | B23: =Sheet1!B23 -> 0 | C23: =Sheet1!C53 -> LAWAL F. A. | D23: =Sheet1!D53 -> 330000 | E23: =Sheet1!E53 -> 43989 | F23: =Sheet1!F53 -> 373989 | G23: =Sheet1!G53 -> 50 | H23: =Sheet1!H53 -> 7479.78 | I23: =Sheet1!I53 -> 879.78 | J23: =Sheet1!J53 -> 6600 | ... Q23: =Sheet1!Q53 -> 0
A24: =Sheet1!A24 -> 22 | B24: =Sheet1!B24 -> 0 | C24: =Sheet1!C60 -> MISS A.D. ADEOYE | D24: =Sheet1!D60 -> 450000 | E24: =Sheet1!E60 -> 59985 | F24: =Sheet1!F60 -> 809985 | G24: =Sheet1!G60 -> 50 | H24: =Sheet1!H60 -> 16199.7 | I24: =Sheet1!I60 -> 1199.7 | J24: =Sheet1!J60 -> 9000 | ... Q24: =Sheet1!Q60 -> 0
A25: =Sheet1!A25 -> 23 | B25: =Sheet1!B25 -> 0 | C25: =Sheet1!C25 -> MISS A.O. ALIMI | D25: =Sheet1!D25 -> 500000 | E25: =Sheet1!E25 -> 66650 | F25: =Sheet1!F25 -> 684985 | G25: =Sheet1!G25 -> 50 | H25: =Sheet1!H25 -> 13699.7 | ... Q25: =Sheet1!Q25 -> 0
A26: =Sheet1!A26 -> 24 | B26: =Sheet1!B26 -> 0 | C26: =Sheet1!C114 -> MISS. ADEMOYE F. M. | D26: =Sheet1!D114 -> 150000 | E26: =Sheet1!E114 -> 19995 | F26: =Sheet1!F114 -> 169995 | G26: =Sheet1!G114 -> 50 | H26: =Sheet1!H114 -> 3399.9 | I26: =Sheet1!I114 -> 399.9 | J26: =Sheet1!J114 -> 3000 | ... Q26: =Sheet1!Q114 -> 0
A27: =Sheet1!A27 -> 25 | B27: =Sheet1!B27 -> 0 | C27: =Sheet1!C137 -> MISS. K. F. KIKIOWO | D27: =Sheet1!D137 -> 450000 | E27: =Sheet1!E137 -> 59985 | F27: =Sheet1!F137 -> 509985 | G27: =Sheet1!G137 -> 50 | H27: =Sheet1!H137 -> 10199.7 | I27: =Sheet1!I137 -> 1199.7 | J27: =Sheet1!J137 -> 9000 | ... Q27: =Sheet1!Q137 -> 0
A28: =Sheet1!A28 -> 26 | B28: =Sheet1!B28 -> 0 | C28: =Sheet1!C19 -> MISS. T. A. ADESOLA | D28: =Sheet1!D19 -> 450000 | E28: =Sheet1!E19 -> 40500 | F28: =Sheet1!F19 -> 478800 | G28: =Sheet1!G19 -> 24 | H28: =Sheet1!H19 -> 19950 | I28: =Sheet1!I19 -> 1687.5 | J28: =Sheet1!J19 -> 18750 | ... Q28: =Sheet1!Q19 -> 0
A29: =Sheet1!A29 -> 27 | B29: =Sheet1!B29 -> 0 | C29: =Sheet1!C94 -> MISS. T. OMOTOSHO | D29: =Sheet1!D94 -> 150000 | E29: =Sheet1!E94 -> 19995 | F29: =Sheet1!F94 -> 169995 | G29: =Sheet1!G94 -> 50 | H29: =Sheet1!H94 -> 3399.9 | I29: =Sheet1!I94 -> 399.9 | J29: =Sheet1!J94 -> 3000 | ... Q29: =Sheet1!Q94 -> 0
A30: =Sheet1!A30 -> 28 | B30: =Sheet1!B30 -> 0 | C30: =Sheet1!C101 -> MORRIS LOLA O. | D30: =Sheet1!D101 -> 150000 | E30: =Sheet1!E101 -> 19995 | F30: =Sheet1!F101 -> 169882.5 | G30: =Sheet1!G101 -> 50 | H30: =Sheet1!H101 -> 3397.65 | I30: =Sheet1!I101 -> 399.9 | J30: =Sheet1!J101 -> 3000 | ... Q30: =Sheet1!Q101 -> 0
A31: =Sheet1!A31 -> 29 | B31: =Sheet1!B31 -> 0 | C31: =Sheet1!C52 -> MR A.A. SODEINDE | D31: =Sheet1!D52 -> 450001 | E31: =Sheet1!E52 -> 59985.133 | F31: =Sheet1!F52 -> 666650 | G31: =Sheet1!G52 -> 50 | H31: =Sheet1!H52 -> 13333 | I31: =Sheet1!I52 -> 1199.7027 | J31: =Sheet1!J52 -> 9000.02 | ... Q31: =Sheet1!Q52 -> 0
A32: =Sheet1!A32 -> 30 | B32: =Sheet1!B32 -> 0 | C32: =Sheet1!C55 -> MR A.A.ADUNMADEHIN | D32: =Sheet1!D55 -> 500000 | E32: =Sheet1!E55 -> 66650 | F32: =Sheet1!F55 -> 424987.5 | G32: =Sheet1!G55 -> 50 | H32: =Sheet1!H55 -> 8499.75 | I32: =Sheet1!I55 -> 1333 | J32: =Sheet1!J55 -> 10000 | ... Q32: =Sheet1!Q55 -> 0
A33: =Sheet1!A33 -> 31 | B33: =Sheet1!B33 -> 0 | C33: =Sheet1!C78 -> MR M.O OLAJIDE | D33: =Sheet1!D78 -> 330000 | E33: =Sheet1!E78 -> 43989 | F33: =Sheet1!F78 -> 373989 | G33: =Sheet1!G78 -> 50 | H33: =Sheet1!H78 -> 7479.78 | I33: =Sheet1!I78 -> 879.78 | J33: =Sheet1!J78 -> 6600 | ... Q33: =Sheet1!Q78 -> 0
A34: =Sheet1!A34 -> 32 | B34: =Sheet1!B34 -> 0 | C34: =Sheet1!C61 -> MR O.E ODUNTAN | D34: =Sheet1!D61 -> 450000 | E34: =Sheet1!E61 -> 59985 | F34: =Sheet1!F61 -> 509985 | G34: =Sheet1!G61 -> 50 | H34: =Sheet1!H61 -> 10199.7 | I34: =Sheet1!I61 -> 1199.7 | J34: =Sheet1!J61 -> 9000 | ... Q34: =Sheet1!Q61 -> 0
A35: =Sheet1!A35 -> 33 | B35: =Sheet1!B35 -> 0 | C35: =Sheet1!C23 -> MR SHOMOYE T.H. | D35: =Sheet1!D23 -> 500000 | E35: =Sheet1!E23 -> 66650 | F35: =Sheet1!F23 -> 509985 | G35: =Sheet1!G23 -> 50 | H35: =Sheet1!H23 -> 10199.7 | I35: =Sheet1!I23 -> 1333 | J35: =Sheet1!J23 -> 10000 | ... Q35: =Sheet1!Q23 -> 0
A36: =Sheet1!A36 -> 34 | B36: =Sheet1!B36 -> 0 | C36: =Sheet1!C121 -> MR T.O. OLOJEDE | D36: =Sheet1!D121 -> 500000 | E36: =Sheet1!E121 -> 66650 | F36: =Sheet1!F121 -> 509985 | G36: =Sheet1!G121 -> 50 | H36: =Sheet1!H121 -> 10199.7 | I36: =Sheet1!I121 -> 1333 | J36: =Sheet1!J121 -> 10000 | ... Q36: =Sheet1!Q121 -> 0
A37: =Sheet1!A37 -> 35 | B37: =Sheet1!B37 -> 0 | C37: =Sheet1!C3 -> MR. A. A. OLADOJA | D37: =Sheet1!D3 -> 500000 | E37: =Sheet1!E3 -> 66650 | F37: =Sheet1!F3 -> 566650 | G37: =Sheet1!G3 -> 50 | H37: =Sheet1!H3 -> 11333 | I37: =Sheet1!I3 -> 1333 | J37: =Sheet1!J3 -> 10000 | ... Q37: =Sheet1!Q3 -> 0
A38: =Sheet1!A38 -> 36 | B38: =Sheet1!B38 -> 0 | C38: =Sheet1!C51 -> MR. A. D. AYOADE | D38: =Sheet1!D51 -> 500000 | E38: =Sheet1!E51 -> 66650 | F38: =Sheet1!F51 -> 566650 | G38: =Sheet1!G51 -> 50 | H38: =Sheet1!H51 -> 11333 | I38: =Sheet1!I51 -> 1333 | J38: =Sheet1!J51 -> 10000 | ... Q38: =Sheet1!Q51 -> 0
A39: =Sheet1!A39 -> 37 | B39: =Sheet1!B39 -> 0 | C39: =Sheet1!C45 -> MR. A. ESAN | D39: =Sheet1!D45 -> 330000 | E39: =Sheet1!E45 -> 43989 | F39: =Sheet1!F45 -> 373989 | G39: =Sheet1!G45 -> 50 | H39: =Sheet1!H45 -> 7479.78 | I39: =Sheet1!I45 -> 879.78 | J39: =Sheet1!J45 -> 6600 | ... Q39: =Sheet1!Q45 -> 0
A40: =Sheet1!A40 -> 38 | B40: =Sheet1!B40 -> 0 | C40: =Sheet1!C64 -> MR. A. L.AWE | D40: =Sheet1!D64 -> 450000 | E40: =Sheet1!E64 -> 59985 | F40: =Sheet1!F64 -> 502322 | G40: =Sheet1!G64 -> 50 | H40: =Sheet1!H64 -> 10046.44 | I40: =Sheet1!I64 -> 1199.7 | J40: =Sheet1!J64 -> 9000 | ... Q40: =Sheet1!Q64 -> 0
A41: =Sheet1!A41 -> 39 | B41: =Sheet1!B41 -> 0 | C41: =Sheet1!C107 -> MR. A. O. ADEFI | D41: =Sheet1!D107 -> 150000 | E41: =Sheet1!E107 -> 19995 | F41: =Sheet1!F107 -> 169995 | G41: =Sheet1!G107 -> 50 | H41: =Sheet1!H107 -> 3399.9 | I41: =Sheet1!I107 -> 399.9 | J41: =Sheet1!J107 -> 3000 | ... Q41: =Sheet1!Q107 -> 0
A42: =Sheet1!A42 -> 40 | B42: =Sheet1!B42 -> 0 | C42: =Sheet1!C58 -> MR. A. T. BAKARE | D42: =Sheet1!D58 -> 450000 | E42: =Sheet1!E58 -> 59985 | F42: =Sheet1!F58 -> 509985 | G42: =Sheet1!G58 -> 50 | H42: =Sheet1!H58 -> 10199.7 | I42: =Sheet1!I58 -> 1199.7 | J42: =Sheet1!J58 -> 9000 | ... Q42: =Sheet1!Q58 -> 0
A43: =Sheet1!A43 -> 41 | B43: =Sheet1!B43 -> 0 | C43: =Sheet1!C115 -> MR. ADELEKE KAZEEM | D43: =Sheet1!D115 -> 150000 | E43: =Sheet1!E115 -> 19995 | F43: =Sheet1!F115 -> 169995 | G43: =Sheet1!G115 -> 50 | H43: =Sheet1!H115 -> 3399.9 | I43: =Sheet1!I115 -> 399.9 | J43: =Sheet1!J115 -> 3000 | ... Q43: =Sheet1!Q115 -> 0
A44: =Sheet1!A44 -> 42 | B44: =Sheet1!B44 -> 0 | C44: =Sheet1!C97 -> MR. ADETOYE ADEDOKUN | D44: =Sheet1!D97 -> 450000 | E44: =Sheet1!E97 -> 59985 | F44: =Sheet1!F97 -> 509985 | G44: =Sheet1!G97 -> 50 | H44: =Sheet1!H97 -> 10199.7 | I44: =Sheet1!I97 -> 1199.7 | J44: =Sheet1!J97 -> 9000 | ... Q44: =Sheet1!Q97 -> 0
A45: =Sheet1!A45 -> 43 | B45: =Sheet1!B45 -> 0 | C45: =Sheet1!C123 -> MR. AFOLABI ABRAHAM | D45: =Sheet1!D123 -> 150000 | E45: =Sheet1!E123 -> 19995 | F45: =Sheet1!F123 -> 169995 | G45: =Sheet1!G123 -> 50 | H45: =Sheet1!H123 -> 3399.9 | I45: =Sheet1!I123 -> 399.9 | J45: =Sheet1!J123 -> 3000 | ... Q45: =Sheet1!Q123 -> 0
A46: =Sheet1!A46 -> 44 | B46: =Sheet1!B46 -> 0 | C46: =Sheet1!C140 -> MR. D.T. DUROTOYE | D46: =Sheet1!D140 -> 150000 | E46: =Sheet1!E140 -> 19995 | F46: =Sheet1!F140 -> 169995 | G46: =Sheet1!G140 -> 50 | H46: =Sheet1!H140 -> 3399.9 | I46: =Sheet1!I140 -> 399.9 | J46: =Sheet1!J140 -> 3000 | ... Q46: =Sheet1!Q140 -> 0
A47: =Sheet1!A47 -> 45 | B47: =Sheet1!B47 -> 0 | C47: =Sheet1!C76 -> MR. F. O. OMOTOSHO | D47: =Sheet1!D76 -> 330000 | E47: =Sheet1!E76 -> 43989 | F47: =Sheet1!F76 -> 373989 | G47: =Sheet1!G76 -> 50 | H47: =Sheet1!H76 -> 7479.78 | I47: =Sheet1!I76 -> 879.78 | J47: =Sheet1!J76 -> 6600 | ... Q47: =Sheet1!Q76 -> 0
A48: =Sheet1!A48 -> 46 | B48: =Sheet1!B48 -> 0 | C48: =Sheet1!C98 -> MR. F. TAIWO | D48: =Sheet1!D98 -> 150000 | E48: =Sheet1!E98 -> 19995 | F48: =Sheet1!F98 -> 169995 | G48: =Sheet1!G98 -> 50 | H48: =Sheet1!H98 -> 3399.9 | I48: =Sheet1!I98 -> 399.9 | J48: =Sheet1!J98 -> 3000 | ... Q48: =Sheet1!Q98 -> 0
A49: =Sheet1!A49 -> 47 | B49: =Sheet1!B49 -> 0 | C49: =Sheet1!C8 -> MR. I. J. OLAGUNJU | D49: =Sheet1!D8 -> 330000 | E49: =Sheet1!E8 -> 43989 | F49: =Sheet1!F8 -> 373989 | G49: =Sheet1!G8 -> 50 | H49: =Sheet1!H8 -> 7479.78 | I49: =Sheet1!I8 -> 879.78 | J49: =Sheet1!J8 -> 6600 | ... Q49: =Sheet1!Q8 -> 0
A50: =Sheet1!A50 -> 48 | B50: =Sheet1!B50 -> 0 | C50: =Sheet1!C13 -> MR. J. B. AYANKOSO | D50: =Sheet1!D13 -> 500000 | E50: =Sheet1!E13 -> 66665 | F50: =Sheet1!F13 -> 566665 | G50: =Sheet1!G13 -> 50 | H50: =Sheet1!H13 -> 11333 | I50: =Sheet1!I13 -> 1333.3 | J50: =Sheet1!J13 -> 10000 | ... Q50: =Sheet1!Q13 -> 0
A51: =Sheet1!A51 -> 49 | B51: =Sheet1!B51 -> 0 | C51: =Sheet1!C75 -> MR. J. O. ALAO | D51: =Sheet1!D75 -> 150000 | E51: =Sheet1!E75 -> 19995 | F51: =Sheet1!F75 -> 169995 | G51: =Sheet1!G75 -> 50 | H51: =Sheet1!H75 -> 3399.9 | I51: =Sheet1!I75 -> 399.9 | J51: =Sheet1!J75 -> 3000 | ... Q51: =Sheet1!Q75 -> 0
A52: =Sheet1!A52 -> 50 | B52: =Sheet1!B52 -> 0 | C52: =Sheet1!C12 -> MR. J. O. AWOTUNDE | D52: =Sheet1!D12 -> 330000 | E52: =Sheet1!E12 -> 43998.9 | F52: =Sheet1!F12 -> 373998.9 | G52: =Sheet1!G12 -> 37 | H52: =Sheet1!H12 -> 10000 | I52: =Sheet1!I12 -> 1189.1595 | J52: =Sheet1!J12 -> 8918.9189 | ... Q52: =Sheet1!Q12 -> 0
A53: =Sheet1!A53 -> 51 | B53: =Sheet1!B53 -> 0 | C53: =Sheet1!C125 -> MR. KADIRI MOHAMMED | D53: =Sheet1!D125 -> 150000 | E53: =Sheet1!E125 -> 19995 | F53: =Sheet1!F125 -> 169995 | G53: =Sheet1!G125 -> 50 | H53: =Sheet1!H125 -> 3399.9 | I53: =Sheet1!I125 -> 399.9 | J53: =Sheet1!J125 -> 3000 | ... Q53: =Sheet1!Q125 -> 0
A54: =Sheet1!A54 -> 52 | B54: =Sheet1!B54 -> 0 | C54: =Sheet1!C135 -> MR. KAYODE TELLA | D54: =Sheet1!D135 -> 150000 | E54: =Sheet1!E135 -> 19995 | F54: =Sheet1!F135 -> 339990 | G54: =Sheet1!G135 -> 50 | H54: =Sheet1!H135 -> 6799.8 | I54: =Sheet1!I135 -> 399.9 | J54: =Sheet1!J135 -> 3000 | ... Q54: =Sheet1!Q135 -> 0
A55: =Sheet1!A55 -> 53 | B55: =Sheet1!B55 -> 0 | C55: =Sheet1!C31 -> MR. KEHINDE ADEOSUN | D55: =Sheet1!D31 -> 450000 | E55: =Sheet1!E31 -> 59985 | F55: =Sheet1!F31 -> 509985 | G55: =Sheet1!G31 -> 50 | H55: =Sheet1!H31 -> 10199.7 | I55: =Sheet1!I31 -> 1199.7 | J55: =Sheet1!J31 -> 9000 | ... Q55: =Sheet1!Q31 -> 0
A56: =Sheet1!A56 -> 54 | B56: =Sheet1!B56 -> 0 | C56: =Sheet1!C42 -> MR. L.K. YUSUFF | D56: =Sheet1!D42 -> 450000 | E56: =Sheet1!E42 -> 59985 | F56: =Sheet1!F42 -> 509985 | G56: =Sheet1!G42 -> 50 | H56: =Sheet1!H42 -> 10199.7 | I56: =Sheet1!I42 -> 1199.7 | J56: =Sheet1!J42 -> 9000 | ... Q56: =Sheet1!Q42 -> 0
A57: =Sheet1!A57 -> 55 | B57: =Sheet1!B57 -> 0 | C57: =Sheet1!C37 -> MR. MARTINS K. O. | D57: =Sheet1!D37 -> 450000 | E57: =Sheet1!E37 -> 59985 | F57: =Sheet1!F37 -> 509985 | G57: =Sheet1!G37 -> 50 | H57: =Sheet1!H37 -> 10199.7 | I57: =Sheet1!I37 -> 1199.7 | J57: =Sheet1!J37 -> 9000 | ... Q57: =Sheet1!Q37 -> 0
A58: =Sheet1!A58 -> 56 | B58: =Sheet1!B58 -> 0 | C58: =Sheet1!C18 -> MR. NASIRU A | D58: =Sheet1!D18 -> 330000 | E58: =Sheet1!E18 -> 29700 | F58: =Sheet1!F18 -> 373989 | G58: =Sheet1!G18 -> 50 | H58: =Sheet1!H18 -> 7479.78 | I58: =Sheet1!I18 -> 594 | J58: =Sheet1!J18 -> 6600 | ... Q58: =Sheet1!Q18 -> 0
A59: =Sheet1!A59 -> 57 | B59: =Sheet1!B59 -> 0 | C59: =Sheet1!C59 -> MR. O. O. ALAO | D59: =Sheet1!D59 -> 330000 | E59: =Sheet1!E59 -> 43989 | F59: =Sheet1!F59 -> 373989 | G59: =Sheet1!G59 -> 50 | H59: =Sheet1!H59 -> 7479.78 | ... Q59: =Sheet1!Q59 -> 0
A60: =Sheet1!A60 -> 58 | B60: =Sheet1!B60 -> 0 | C60: =Sheet1!C100 -> MR. O. OSUNLANA | D60: =Sheet1!D100 -> 330000 | E60: =Sheet1!E100 -> 43989 | F60: =Sheet1!F100 -> 373989 | G60: =Sheet1!G100 -> 50 | H60: =Sheet1!H100 -> 7479.78 | I60: =Sheet1!I100 -> 879.78 | J60: =Sheet1!J100 -> 6600 | ... Q60: =Sheet1!Q100 -> 0
A61: =Sheet1!A61 -> 59 | B61: =Sheet1!B61 -> 0 | C61: =Sheet1!C110 -> MR. OLADOKUN JIMOH | D61: =Sheet1!D110 -> 150000 | E61: =Sheet1!E110 -> 19995 | F61: =Sheet1!F110 -> 169995 | G61: =Sheet1!G110 -> 50 | H61: =Sheet1!H110 -> 3399.9 | I61: =Sheet1!I110 -> 399.9 | J61: =Sheet1!J110 -> 3000 | ... Q61: =Sheet1!Q110 -> 0
A62: =Sheet1!A62 -> 60 | B62: =Sheet1!B62 -> 0 | C62: =Sheet1!C6 -> MR. OLUSEYE ABODERIN | D62: =Sheet1!D6 -> 450000 | E62: =Sheet1!E6 -> 59985 | F62: =Sheet1!F6 -> 509985 | G62: =Sheet1!G6 -> 50 | H62: =Sheet1!H6 -> 10199.7 | I62: =Sheet1!I6 -> 1199.7 | J62: =Sheet1!J6 -> 9000 | ... Q62: =Sheet1!Q6 -> 0
A63: =Sheet1!A63 -> 61 | B63: =Sheet1!B63 -> 0 | C63: =Sheet1!C120 -> MR. OLUSOLA O. OMONIYI | D63: =Sheet1!D120 -> 330000 | E63: =Sheet1!E120 -> 43989 | F63: =Sheet1!F120 -> 373989 | G63: =Sheet1!G120 -> 50 | H63: =Sheet1!H120 -> 7479.78 | I63: =Sheet1!I120 -> 879.78 | J63: =Sheet1!J120 -> 6600 | ... Q63: =Sheet1!Q120 -> 0
A64: =Sheet1!A64 -> 62 | B64: =Sheet1!B64 -> 0 | C64: =Sheet1!C129 -> MR. ONWUCHEKA I | D64: =Sheet1!D129 -> 150000 | E64: =Sheet1!E129 -> 19995 | F64: =Sheet1!F129 -> 169995 | G64: =Sheet1!G129 -> 50 | H64: =Sheet1!H129 -> 3399.9 | I64: =Sheet1!I129 -> 399.9 | J64: =Sheet1!J129 -> 3000 | ... Q64: =Sheet1!Q129 -> 0
A65: =Sheet1!A65 -> 63 | B65: =Sheet1!B65 -> 0 | C65: =Sheet1!C127 -> MR. OPASINA KOLAWOLE | D65: =Sheet1!D127 -> 250000 | E65: =Sheet1!E127 -> 33325 | F65: =Sheet1!F127 -> 258331.2 | G65: =Sheet1!G127 -> 15 | H65: =Sheet1!H127 -> 17222.08 | I65: =Sheet1!I127 -> 2221.6667 | J65: =Sheet1!J127 -> 16666.667 | ... Q65: =Sheet1!Q127 -> 0
A66: =Sheet1!A66 -> 64 | B66: =Sheet1!B66 -> 0 | C66: =Sheet1!C16 -> MR. OTITOLOJU O. ADISA | D66: =Sheet1!D16 -> 500000 | E66: =Sheet1!E16 -> 66650 | F66: =Sheet1!F16 -> 566650 | G66: =Sheet1!G16 -> 50 | H66: =Sheet1!H16 -> 11333 | I66: =Sheet1!I16 -> 1333 | J66: =Sheet1!J16 -> 10000 | ... Q66: =Sheet1!Q16 -> 0
A67: =Sheet1!A67 -> 65 | B67: =Sheet1!B67 -> 0 | C67: =Sheet1!C116 -> MR. OYEDOTUN ISIAKA | D67: =Sheet1!D116 -> 150000 | E67: =Sheet1!E116 -> 19995 | F67: =Sheet1!F116 -> 169995 | G67: =Sheet1!G116 -> 50 | H67: =Sheet1!H116 -> 3399.9 | I67: =Sheet1!I116 -> 399.9 | J67: =Sheet1!J116 -> 3000 | ... Q67: =Sheet1!Q116 -> 0
A68: =Sheet1!A68 -> 66 | B68: =Sheet1!B68 -> 0 | C68: =Sheet1!C139 -> MR. S. A. ADEJINMI | D68: =Sheet1!D139 -> 330000 | E68: =Sheet1!E139 -> 43989 | F68: =Sheet1!F139 -> 373989 | G68: =Sheet1!G139 -> 50 | H68: =Sheet1!H139 -> 7479.78 | I68: =Sheet1!I139 -> 879.78 | J68: =Sheet1!J139 -> 6600 | ... Q68: =Sheet1!Q139 -> 0
A69: =Sheet1!A69 -> 67 | B69: =Sheet1!B69 -> 0 | C69: =Sheet1!C86 -> MR. S. AWE | D69: =Sheet1!D86 -> 150000 | E69: =Sheet1!E86 -> 19995 | F69: =Sheet1!F86 -> 169995 | G69: =Sheet1!G86 -> 50 | H69: =Sheet1!H86 -> 3399.9 | I69: =Sheet1!I86 -> 399.9 | J69: =Sheet1!J86 -> 3000 | ... Q69: =Sheet1!Q86 -> 0
A70: =Sheet1!A70 -> 68 | B70: =Sheet1!B70 -> 0 | C70: =Sheet1!C56 -> MR. S. G. OSINEYE | D70: =Sheet1!D56 -> 330000 | E70: =Sheet1!E56 -> 43989 | F70: =Sheet1!F56 -> 373989 | G70: =Sheet1!G56 -> 50 | H70: =Sheet1!H56 -> 7479.78 | I70: =Sheet1!I56 -> 879.78 | J70: =Sheet1!J56 -> 6600 | ... Q70: =Sheet1!Q56 -> 0
A71: =Sheet1!A71 -> 69 | B71: =Sheet1!B71 -> 0 | C71: =Sheet1!C50 -> MR. S. T. AMOO | D71: =Sheet1!D50 -> 450000 | E71: =Sheet1!E50 -> 59985 | F71: =Sheet1!F50 -> 509985 | G71: =Sheet1!G50 -> 50 | H71: =Sheet1!H50 -> 10199.7 | I71: =Sheet1!I50 -> 1199.7 | J71: =Sheet1!J50 -> 9000 | ... Q71: =Sheet1!Q50 -> 0
A72: =Sheet1!A72 -> 70 | B72: =Sheet1!B72 -> 0 | C72: =Sheet1!C102 -> MR. SAHEED G. ABIOYE | D72: =Sheet1!D102 -> 330000 | E72: =Sheet1!E102 -> 43989 | F72: =Sheet1!F102 -> 373989 | G72: =Sheet1!G102 -> 50 | H72: =Sheet1!H102 -> 7479.78 | I72: =Sheet1!I102 -> 879.78 | J72: =Sheet1!J102 -> 6600 | ... Q72: =Sheet1!Q102 -> 0
A73: =Sheet1!A73 -> 71 | B73: =Sheet1!B73 -> 0 | C73: =Sheet1!C134 -> MR. SHAMSUDEEN N. B. | D73: =Sheet1!D134 -> 150000 | E73: =Sheet1!E134 -> 19995 | F73: =Sheet1!F134 -> 169995 | G73: =Sheet1!G134 -> 50 | H73: =Sheet1!H134 -> 3399.9 | I73: =Sheet1!I134 -> 399.9 | J73: =Sheet1!J134 -> 3000 | ... Q73: =Sheet1!Q134 -> 0
A74: =Sheet1!A74 -> 72 | B74: =Sheet1!B74 -> 0 | C74: =Sheet1!C119 -> MRS A. OBASOOTO | D74: =Sheet1!D119 -> 450000 | E74: =Sheet1!E119 -> 59985 | F74: =Sheet1!F119 -> 424987.5 | G74: =Sheet1!G119 -> 50 | H74: =Sheet1!H119 -> 8499.75 | I74: =Sheet1!I119 -> 1199.7 | J74: =Sheet1!J119 -> 9000 | ... Q74: =Sheet1!Q119 -> 0
A75: =Sheet1!A75 -> 73 | B75: =Sheet1!B75 -> 0 | C75: =Sheet1!C22 -> MRS ADEROUNMU | D75: =Sheet1!D22 -> 500000 | E75: =Sheet1!E22 -> 66650 | F75: =Sheet1!F22 -> 527191.92 | G75: =Sheet1!G22 -> 24 | H75: =Sheet1!H22 -> 21966.33 | I75: =Sheet1!I22 -> 2777.0833 | J75: =Sheet1!J22 -> 20833.333 | ... Q75: =Sheet1!Q22 -> 0
A76: =Sheet1!A76 -> 74 | B76: =Sheet1!B76 -> 0 | C76: =Sheet1!C11 -> MRS ADEYEYE-KUKU O.O | D76: =Sheet1!D11 -> 450000 | E76: =Sheet1!E11 -> 59985 | F76: =Sheet1!F11 -> 509985 | G76: =Sheet1!G11 -> 50 | H76: =Sheet1!H11 -> 9999.75 | I76: =Sheet1!I11 -> 1199.7 | J76: =Sheet1!J11 -> 9000 | ... Q76: =Sheet1!Q11 -> 0
A77: =Sheet1!A77 -> 75 | B77: =Sheet1!B77 -> 0 | C77: =Sheet1!C96 -> MRS B.O. ADESIDA | D77: =Sheet1!D96 -> 150001 | E77: =Sheet1!E96 -> 19995.133 | F77: =Sheet1!F96 -> 169995 | G77: =Sheet1!G96 -> 50 | H77: =Sheet1!H96 -> 3399.9 | I77: =Sheet1!I96 -> 399.90267 | J77: =Sheet1!J96 -> 3000.02 | ... Q77: =Sheet1!Q96 -> 0
A78: =Sheet1!A78 -> 76 | B78: =Sheet1!B78 -> 0 | C78: =Sheet1!C39 -> MRS D.I KOMOLAFE | D78: =Sheet1!D39 -> 450000 | E78: =Sheet1!E39 -> 59985 | F78: =Sheet1!F39 -> 566650 | G78: =Sheet1!G39 -> 50 | H78: =Sheet1!H39 -> 11333 | I78: =Sheet1!I39 -> 1199.7 | J78: =Sheet1!J39 -> 9000 | ... Q78: =Sheet1!Q39 -> 0
A79: =Sheet1!A79 -> 77 | B79: =Sheet1!B79 -> 0 | C79: =Sheet1!C70 -> MRS K.O OKIN | D79: =Sheet1!D70 -> 500000 | E79: =Sheet1!E70 -> 66650 | F79: =Sheet1!F70 -> 424987.5 | G79: =Sheet1!G70 -> 50 | H79: =Sheet1!H70 -> 8499.75 | I79: =Sheet1!I70 -> 1333 | J79: =Sheet1!J70 -> 10000 | ... Q79: =Sheet1!Q70 -> 0
A80: =Sheet1!A80 -> 78 | B80: =Sheet1!B80 -> 0 | C80: =Sheet1!C10 -> MRS O.F. STANLEY JOHN | D80: =Sheet1!D10 -> 450000 | E80: =Sheet1!E10 -> 59985 | F80: =Sheet1!F10 -> 509985 | G80: =Sheet1!G10 -> 50 | H80: =Sheet1!H10 -> 13699.7 | I80: =Sheet1!I10 -> 1199.7 | J80: =Sheet1!J10 -> 9000 | ... Q80: =Sheet1!Q10 -> 0
A81: =Sheet1!A81 -> 79 | B81: =Sheet1!B81 -> 0 | C81: =Sheet1!C24 -> MRS O.O ADENUGA | D81: =Sheet1!D24 -> 500000 | E81: =Sheet1!E24 -> 66650 | F81: =Sheet1!F24 -> 509985 | G81: =Sheet1!G24 -> 50 | H81: =Sheet1!H24 -> 10199.7 | I81: =Sheet1!I24 -> 1333 | J81: =Sheet1!J24 -> 10000 | ... Q81: =Sheet1!Q24 -> 0
A82: =Sheet1!A82 -> 80 | B82: =Sheet1!B82 -> 0 | C82: =Sheet1!C33 -> MRS O.T. ADESINA | D82: =Sheet1!D33 -> 330000 | E82: =Sheet1!E33 -> 43989 | F82: =Sheet1!F33 -> 373989 | G82: =Sheet1!G33 -> 50 | H82: =Sheet1!H33 -> 7479.78 | I82: =Sheet1!I33 -> 879.78 | J82: =Sheet1!J33 -> 6600 | ... Q82: =Sheet1!Q33 -> 0
A83: =Sheet1!A83 -> 81 | B83: =Sheet1!B83 -> 0 | C83: =Sheet1!C44 -> MRS R.A. KOLAWOLE | D83: =Sheet1!D44 -> 500000 | E83: =Sheet1!E44 -> 66650 | F83: =Sheet1!F44 -> 424987.5 | G83: =Sheet1!G44 -> 50 | H83: =Sheet1!H44 -> 8499.75 | I83: =Sheet1!I44 -> 1333 | J83: =Sheet1!J44 -> 10000 | ... Q83: =Sheet1!Q44 -> 0
A84: =Sheet1!A84 -> 82 | B84: =Sheet1!B84 -> 0 | C84: =Sheet1!C79 -> MRS. A. A. ADEOYE | D84: =Sheet1!D79 -> 330000 | E84: =Sheet1!E79 -> 43989 | F84: =Sheet1!F79 -> 373989 | G84: =Sheet1!G79 -> 50 | H84: =Sheet1!H79 -> 7479.78 | I84: =Sheet1!I79 -> 879.78 | J84: =Sheet1!J79 -> 6600 | ... Q84: =Sheet1!Q79 -> 0
A85: =Sheet1!A85 -> 83 | B85: =Sheet1!B85 -> 0 | C85: =Sheet1!C7 -> MRS. A. B. FOLAHAN | D85: =Sheet1!D7 -> 150000 | E85: =Sheet1!E7 -> 19995 | F85: =Sheet1!F7 -> 169995 | G85: =Sheet1!G7 -> 50 | H85: =Sheet1!H7 -> 3399.9 | I85: =Sheet1!I7 -> 399.9 | J85: =Sheet1!J7 -> 3000 | ... Q85: =Sheet1!Q7 -> 0
A86: =Sheet1!A86 -> 84 | B86: =Sheet1!B86 -> 0 | C86: =Sheet1!C49 -> MRS. A. T. TIJANI | D86: =Sheet1!D49 -> 330000 | E86: =Sheet1!E49 -> 43989 | F86: =Sheet1!F49 -> 373989 | G86: =Sheet1!G49 -> 50 | H86: =Sheet1!H49 -> 7479.78 | I86: =Sheet1!I49 -> 879.78 | J86: =Sheet1!J49 -> 6600 | ... Q86: =Sheet1!Q49 -> 0
A87: =Sheet1!A87 -> 85 | B87: =Sheet1!B87 -> 0 | C87: =Sheet1!C43 -> MRS. A. YUSUFF | D87: =Sheet1!D43 -> 330000 | E87: =Sheet1!E43 -> 43989 | F87: =Sheet1!F43 -> 373989 | G87: =Sheet1!G43 -> 50 | H87: =Sheet1!H43 -> 7479.78 | I87: =Sheet1!I43 -> 879.78 | J87: =Sheet1!J43 -> 6600 | ... Q87: =Sheet1!Q43 -> 0
A88: =Sheet1!A88 -> 86 | B88: =Sheet1!B88 -> 0 | C88: =Sheet1!C111 -> MRS. ADELKE FOLASADE D | D88: =Sheet1!D111 -> 330000 | E88: =Sheet1!E111 -> 43989 | F88: =Sheet1!F111 -> 373989 | G88: =Sheet1!G111 -> 50 | H88: =Sheet1!H111 -> 7479.78 | I88: =Sheet1!I111 -> 879.78 | J88: =Sheet1!J111 -> 6600 | ... Q88: =Sheet1!Q111 -> 0
A89: =Sheet1!A89 -> 87 | B89: =Sheet1!B89 -> 0 | C89: =Sheet1!C17 -> MRS. ADEUGA M.M. | D89: =Sheet1!D17 -> 500000 | E89: =Sheet1!E17 -> 45000 | F89: =Sheet1!F17 -> 566650 | G89: =Sheet1!G17 -> 50 | H89: =Sheet1!H17 -> 11333 | I89: =Sheet1!I17 -> 900 | J89: =Sheet1!J17 -> 10000 | ... Q89: =Sheet1!Q17 -> 0
A90: =Sheet1!A90 -> 88 | B90: =Sheet1!B90 -> 0 | C90: =Sheet1!C71 -> MRS. B. F. ADEYEMI | D90: =Sheet1!D71 -> 330000 | E90: =Sheet1!E71 -> 43989 | F90: =Sheet1!F71 -> 373989 | G90: =Sheet1!G71 -> 50 | H90: =Sheet1!H71 -> 7479.78 | I90: =Sheet1!I71 -> 879.78 | J90: =Sheet1!J71 -> 6600 | ... Q90: =Sheet1!Q71 -> 0
A91: =Sheet1!A91 -> 89 | B91: =Sheet1!B91 -> 0 | C91: =Sheet1!C133 -> MRS. B. O. OLARIBIGBE | D91: =Sheet1!D133 -> 330000 | E91: =Sheet1!E133 -> 43989 | F91: =Sheet1!F133 -> 373989 | G91: =Sheet1!G133 -> 50 | H91: =Sheet1!H133 -> 7479.78 | I91: =Sheet1!I133 -> 879.78 | J91: =Sheet1!J133 -> 6600 | ... Q91: =Sheet1!Q133 -> 0
A92: =Sheet1!A92 -> 90 | B92: =Sheet1!B92 -> 0 | C92: =Sheet1!C9 -> MRS. B. O. SOMIDE | D92: =Sheet1!D9 -> 450000 | E92: =Sheet1!E9 -> 59985 | F92: =Sheet1!F9 -> 509985 | G92: =Sheet1!G9 -> 50 | H92: =Sheet1!H9 -> 10199.7 | I92: =Sheet1!I9 -> 1199.7 | J92: =Sheet1!J9 -> 9000 | ... Q92: =Sheet1!Q9 -> 0
A93: =Sheet1!A93 -> 91 | B93: =Sheet1!B93 -> 0 | C93: =Sheet1!C36 -> MRS. B.S. ODEMAKINDE | D93: =Sheet1!D36 -> 500000 | E93: =Sheet1!E36 -> 66650 | F93: =Sheet1!F36 -> 708312.5 | G93: =Sheet1!G36 -> 50 | H93: =Sheet1!H36 -> 14166.25 | I93: =Sheet1!I36 -> 1333 | J93: =Sheet1!J36 -> 10000 | ... Q93: =Sheet1!Q36 -> 0
A94: =Sheet1!A94 -> 92 | B94: =Sheet1!B94 -> 0 | C94: =Sheet1!C104 -> MRS. D. O. ABODUNDE | D94: =Sheet1!D104 -> 150000 | E94: =Sheet1!E104 -> 19995 | F94: =Sheet1!F104 -> 169995 | G94: =Sheet1!G104 -> 50 | H94: =Sheet1!H104 -> 3399.9 | I94: =Sheet1!I104 -> 399.9 | J94: =Sheet1!J104 -> 3000 | ... Q94: =Sheet1!Q104 -> 0
A95: =Sheet1!A95 -> 93 | B95: =Sheet1!B95 -> 0 | C95: =Sheet1!C81 -> MRS. E. M. ABEGUNDE | D95: =Sheet1!D81 -> 450000 | E95: =Sheet1!E81 -> 59985 | F95: =Sheet1!F81 -> 509995 | G95: =Sheet1!G81 -> 50 | H95: =Sheet1!H81 -> 10199.9 | I95: =Sheet1!I81 -> 1199.7 | J95: =Sheet1!J81 -> 9000 | ... Q95: =Sheet1!Q81 -> 0
A96: =Sheet1!A96 -> 94 | B96: =Sheet1!B96 -> 0 | C96: =Sheet1!C85 -> MRS. E. O. OMOJUWA | D96: =Sheet1!D85 -> 330000 | E96: =Sheet1!E85 -> 43989 | F96: =Sheet1!F85 -> 351114.72 | G96: =Sheet1!G85 -> 24 | H96: =Sheet1!H85 -> 14629.78 | I96: =Sheet1!I85 -> 1832.875 | J96: =Sheet1!J85 -> 13750 | ... Q96: =Sheet1!Q85 -> 0
A97: =Sheet1!A97 -> 95 | B97: =Sheet1!B97 -> 0 | C97: =Sheet1!C109 -> MRS. F. AYENI | D97: =Sheet1!D109 -> 150000 | E97: =Sheet1!E109 -> 19995 | F97: =Sheet1!F109 -> 169995 | G97: =Sheet1!G109 -> 50 | H97: =Sheet1!H109 -> 3399.9 | I97: =Sheet1!I109 -> 399.9 | J97: =Sheet1!J109 -> 3000 | ... Q97: =Sheet1!Q109 -> 0
A98: =Sheet1!A98 -> 96 | B98: =Sheet1!B98 -> 0 | C98: =Sheet1!C77 -> MRS. F. B. OLAMILETRILLION | D98: =Sheet1!D77 -> 330000 | E98: =Sheet1!E77 -> 43989 | F98: =Sheet1!F77 -> 373989 | G98: =Sheet1!G77 -> 50 | H98: =Sheet1!H77 -> 7479.78 | I98: =Sheet1!I77 -> 879.78 | J98: =Sheet1!J77 -> 6600 | ... Q98: =Sheet1!Q77 -> 0
A99: =Sheet1!A99 -> 97 | B99: =Sheet1!B99 -> 0 | C99: =Sheet1!C118 -> MRS. F. O. OLAGUNJU | D99: =Sheet1!D118 -> 150000 | E99: =Sheet1!E118 -> 19995 | F99: =Sheet1!F118 -> 169995 | G99: =Sheet1!G118 -> 50 | H99: =Sheet1!H118 -> 3399.9 | I99: =Sheet1!I118 -> 399.9 | J99: =Sheet1!J118 -> 3000 | ... Q99: =Sheet1!Q118 -> 0
A100: =Sheet1!A100 -> 98 | B100: =Sheet1!B100 -> 0 | C100: =Sheet1!C106 -> MRS. J. A. OWOADE | D100: =Sheet1!D106 -> 330000 | E100: =Sheet1!E106 -> 43989 | F100: =Sheet1!F106 -> 373989 | G100: =Sheet1!G106 -> 50 | H100: =Sheet1!H106 -> 7479.78 | I100: =Sheet1!I106 -> 879.78 | J100: =Sheet1!J106 -> 6600 | ... Q100: =Sheet1!Q106 -> 0
...

Sheet Sheet3
A1: staff' Name | B1: Car Loan | C1: S/N | D1: REF. I.D | E1: STAFF NAME | F1: MONTHLY DED N
A2: ODETUNDE A. O. | B2: 11333 | C2: 1 | D2: 0 | E2: MRS. ODETUNDE A. O. | F2: 11333
A3: ADENIRAN ADEWALE O | B3: 10199.7 | C3: 2 | D3: 0 | E3: ADENIRAN ADEWALE O | F3: 10199.7
A4: LAMIDI-HUSSEIN K. O | B4: 10199.7 | C4: 3 | D4: 0 | E4: LAMIDI-HUSSEIN K. O | F4: 10199.7
A5: OLANIYAN OLUYEMI | B5: 10199.7 | C5: 4 | D5: 0 | E5: OLANIYAN OLUYEMI | F5: 10199.7
A6: ADENUGA JUMOKE A. | B6: 7479.78 | C6: 6 | D6: 0 | E6: ADENUGA JUMOKE A. | F6: 7479.78
A7: OLAGUNJU F. O. | B7: 7479.78 | C7: 7 | D7: 0 | E7: OLAGUNJU F. O. | F7: 7479.78
A8: LAWAL ADENIKE M. | B8: 7479.78 | C8: 8 | D8: 0 | E8: LAWAL ADENIKE M. | F8: 7479.78
A9: ABIFARIN TOYIN | B9: 7479.78 | C9: 9 | D9: 0 | E9: ABIFARIN TOYIN | F9: 7479.78
A10: ALABI FUNMILAYO S. | B10: 7479.78 | C10: 10 | D10: 0 | E10: ALABI FUNMILAYO S. | F10: 7479.78
A11: ADEGOKE SAMSON A. | B11: 3399.9 | C11: 11 | D11: 0 | E11: ADEGOKE SAMSON A. | F11: 3399.9
A12: KAREEM SHAKIRUDEEN O. | B12: 1699.95 | C12: 12 | D12: 0 | E12: KAREEM SHAKIRUDEEN O. | F12: 1699.95
A13: AKINDUNNI OLUWAJUMOKE A. | B13: 7479.78 | C13: 13 | D13: 0 | E13: MR. I. J. OLAGUNJU | F13: 7479.78
... A41: BAMIRO M. A. | B41: 11333 | C41: 42 | D41: 0 | E41: BAMIRO M. A. | F41: 11333
A42: ODEMAKINDE B. S. | B42: 11333 | C42: 43 | E42: MRS. B.S. ODEMAKINDE | F42: 11333
A43: ADEBOYA O. O. | B43: 10199.7 | C43: 44 | D43: 0 | E43: ADEBOYA O. O. | F43: 10199.7
A44: FALANA V. O. | B44: 10199.7 | C44: 45 | D44: 0 | E44: FALANA V. O. | F44: 10199.7
A45: YUSUFF F. D. | B45: 7479.78 | C45: 46 | D45: 0 | E45: YUSUFF F. D. | F45: 7479.78
A46: OYENIRAN E. T. | B46: 7479.78 | C46: 47 | D46: 0 | E46: E. T. OYENIRAN | F46: 7479.78
A47: AWEDA R. S. | B47: 7479.78 | C47: 48 | D47: 0 | E47: MR. AWEDA R. S | F47: 7479.78
A48: ADEBAYO O. T. | B48: 7479.78 | C48: 50 | D48: 0 | E48: ADEBAYO O. T. | F48: 7479.78
A49: KAZEEM OLUJOKE | B49: 11333 | C49: 51 | D49: 0 | E49: KAZEEM OLUJOKE | F49: 11333
A50: YUSUFF ADIJAT | B50: 7479.78 | C50: 52 | D50: 0 | E50: OLANIYAN MISTURA B. | F50: 7479.78
A51: OLANIYAN MISTURA B. | B51: 7479.78 | C51: 53 | D51: 0 | E51: MRS. A. YUSUFF | F51: 7479.78
A52: OLUGBILE OPEOLU J. | B52: 13699.7 | C52: 54 | D52: 0 | E52: FOLORUNSO. O. MODUPE | F52: 7479.78
A53: FOLORUNSO. O. MODUPE | B53: 7479.78 | C53: 55 | D53: 0 | E53: ALADE VICTORIA A. | F53: 7479.78
A54: ALADE VICTORIA A. | B54: 7479.78 | C54: 56 | D54: 0 | E54: SALAMI TOYIN O. | F54: 7479.78
... A58: KOLAWOLE RUTH A. | B58: 12979.78 | C58: 60 | D58: 0 | E58: MR. A. ESAN | F58: 7479.78
A59: ADEBISI ALIRAT T. | B59: 3399.9 | C59: 61 | E59: MRS. O. J. ODUGBO | F59: 13699.7
A60: ELEGBEDE CHRISTIANAH | B60: 10199.7 | C60: 62 | D60: 0 | E60: ELEGBEDE CHRISTIANAH | F60: 10199.7
A61: FALADE ADEKUNLE G. | B61: 10199.7 | C61: 63 | D61: 0 | E61: A. FALADE | F61: 10199.7
A62: AKINPELU ABIODUN | B62: 10199.7 | C62: 64 | D62: 0 | E62: AKINPELU ABIODUN | F62: 10199.7
A63: Mrs A. T. Tijani | B63: 7479.78 | C63: 66 | D63: 0 | E63: MRS. A. T. TIJANI | F63: 7479.78
A64: BAKARE A. T. | B64: 15999.75 | C64: 67 | D64: 0 | E64: BAKARE A. T. | F64: 15999.75
A65: LAWAL F. A. | B65: 7479.78 | C65: 68 | D65: 0 | E65: LAWAL F. A. | F65: 7479.78
A66: MRS. M.K. SAFIU OLALERE | B66: 7479.78 | C66: 69 | D66: 0 | E66: SAFIU-OLALERE S, K | F66: 7479.78
A67: ADEGBAYI I. A. | B67: 7479.78 | C67: 70 | D67: 0 | E67: ADEGBAYI I. A. | F67: 7479.78
A68: OSINEYE S. G. | B68: 7479.78 | C68: 71 | D68: 0 | E68: MR. S. G. OSINEYE | F68: 7479.78
A69: OYINLOLA R. T. | B69: 7479.78 | C69: 72 | D69: 0 | E69: OYINLOLA R. T. | F69: 7479.78
A70: TIJANI S. D. | B70: 7479.78 | C70: 73 | D70: 0 | E70: TIJANI S. D. | F70: 7479.78
A71: ALAO O. O. | B71: 7479.78 | C71: 74 | D71: 0 | E71: MR. O. O. ALAO | F71: 7479.78
... A98: OLAYINKA A. | B98: 3399.9 | C98: 103 | D98: 0 | E98: OLAYINKA A. | F98: 3399.9
A99: OMOTOSHO F. O. | B99: 7479.78 | C99: 104 | E99: MR. F. O. OMOTOSHO | F99: 7479.78
A100: OYEJIDE F. O. | B100: 10199.9 | C100: 105 | D100: 0 | E100: OYEJIDE F. O. | F100: 10199.9
A101: AYOADE M. O. | B101: 7479.78 | C101: 106 | D101: 0 | E101: MRS. M. O. AYOADE | F101: 7479.78
A102: ADEPOJU A. | B102: 7479.89 | C102: 107 | D102: 0 | E102: ADEPOJU A. | F102: 7479.89
A103: BABATUNDE T. I. | B103: 7479.78 | C103: 108 | D103: 0 | E103: BABATUNDE T. I. | F103: 7479.78
A104: OLADEPO T. S. | B104: 7479.89 | C104: 109 | D104: 0 | E104: OLADEPO T. S. | F104: 7479.89
A105: ENIOLA E. O. | B105: 3399.9 | C105: 110 | D105: 0 | E105: ENIOLA E. O. | F105: 3399.9
A106: OPEYEMI-AKORO O. R. | B106: 3399.9 | C106: 111 | D106: 0 | E106: OPEYEMI-AKORO O. R. | F106: 3399.9
A107: SHODE JELILI O. | B107: 7479.89 | C107: 112 | D107: 0 | E107: SHODE JELILI O. | F107: 7479.89
A108: ASOLO O. ADEBOLA | B108: 3399.9 | C108: 113 | D108: 0 | E108: QOSIM SAUDAT A. | F108: 0
A109: QOSIM SAUDAT A. | B109: 3399.9 | C109: 114 | D109: 0 | E109: ALADE O. S. | F109: 0
A110: ABIOLA OYETUNDE | B110: 3399.9 | C110: 115 | D110: 0 | E110: ADAMS TAIWO | F110: 3399.9
A111: OLAIFA SUNMOLA | B111: 3399.9 | C111: 116 | D111: 0 | E111: SEJINRIN KEMI C. | F111: 3399.9
... A137: OLALEKAN L.O. | B137: 0 | C137: 142 | D137: 0 | E137: MR. OLADOKUN JIMOH | F137: 3399.9
A138: KUKU ESTHER F. | C138: 143 | E138: MRS. O. D. ADESOLA | F138: 6799.8
A139: OYEBODE T.I. | B139: 0 | C139: 144 | D139: 0 | E139: ODUFUWA-ABAYOMI O. A. | F139: 7479.78
A140: AJEWUMI M.A. | B140: 0 | C140: 145 | D140: 0 | E140: MR. AFOLABI ABRAHAM | F140: 3399.9
A141: Mrs S. Adediran karimu | B141: 0 | C141: 146 | D141: 0 | E141: ABIOYE N.HASSAN | F141: 3399.9
A142: Grand Total | B142: =SUM(B106:B141) -> 44878.79 | C142: 147 | D142: 0 | E142: ARANSI MUKAILA | F142: 3399.9
C143: 148 | D143: 0 | E143: BELLO SAIDAT | F143: 3399.9
C144: 149 | D144: 0 | E144: AJAYI ADEOLA O. | F144: 3399.9
C145: 150 | D145: 0 | E145: AYOOLA SAUDAT O. | F145: 3399.9
C146: 151 | D146: 0 | E146: MR. KADIRI MOHAMMED | F146: 3399.9
C147: 152 | D147: 0 | E147: YEKEEN MOJEED | F147: 3399.9
C148: 153 | D148: 0 | E148: OLAYIWOLA R. A. | F148: 3399.9
C149: 154 | D149: * | E149: OHU ABOSEDE | F149: 3399.9
C150: 155 | E150: MR. OLATUNJI ADEREMI | F150: 3399.9
C151: 156 | E151: SANNI OLUWOLE O. | F151: 3399.9
C152: 157 | E152: ADEGOKE GAFAR | F152: 3399.9
A153: staff' Name | B153: Car Loan | C153: 158 | E153: ADERINKOMI ADETAYO J. | F153: 3399.9
A154: OLABAMIJI ADETUTU A. | B154: 7479.78 | C154: 159 | E154: ASAOLU OYEWOLE | F154: 3399.9
A155: OSUNLANA O. | B155: 7479.78 | C155: 160 | E155: EWUOLA LAWRENCE | F155: 3399.9
A156: YUSUFF MUJIDAT O. | B156: 14629.78 | C156: 161 | E156: HARUNA RILIWANU | F156: 3399.9
A157: ABASS TAIWO A. | B157: 0 | C157: 162 | E157: OGUNSOLA EMMANUEL O. | F157: 3399.9
A158: ABIOYE SAHEED G. | B158: 7479.78 | C158: 163 | E158: MR. ONWUCHEKA I | F158: 3399.9
A159: ADEKUNLE SAKIRAT B. | B159: 0 | C159: 164 | E159: MR. SAMSON OJO | F159: 3399.9
A160: ADELEKE FOLASADE D. | C160: 165 | E160: RAJI TAIWO T. | F160: 10199.7
A161: OLAOLUWA MAGRET O. | B161: 0 | C161: 166 | E161: AJADI CORNELIUS A. | F161: 7479.78
A162: OWOADE J. A | B162: 7479.78 | C162: 167 | E162: MUSTAPHA DAUDA | F162: 7479.78
A163: OWOADE R. O. | B163: 7479.78 | C163: 168 | E163: ADEDEJI YISAU | F163: 3399.9
A164: DURODOLA YETUNDE TOLA | B164: 0 | C164: 169 | E164: O. ADEWOYIN | F164: 3399.9
A165: SHOLAJA WAHEED A. | B165: 0 | C165: 170 | E165: ABORISADE MOLIK | F165: 7479.78
A166: ADEMOYE FOLASADE M. | B166: 0 | C166: 171 | E166: LAMIDI RAMONI | F166: 7479.78
A167: ADEOTI .V. | C167: 172 | E167: KAREEM KAMORU | F167: 7479.78
A168: ALUKO OLUWAKEMI Y. | B168: 3399.9 | C168: 173 | E168: BUSARI NURENI | F168: 7479.78
A169: ANIPUPO OLUSEGUN | B169: 0 | C169: 174 | E169: GAFARI MAKINDE | F169: 7479.78
A170: IBITOKUN AYODELE O. | B170: 3399.9 | C170: 175 | E170: LAMIDI TAJUDEEN | F170: 7479.78
A171: OYINLOLA IDAYAT | B171: 3399.9 | C171: 176 | E171: ALIMI I.A | F171: 7479.78
A172: SHITTU AZEEZ A. | B172: 0 | C172: 177 | E172: OYEDIRAN TIRIMISIYU | F172: 3399.9
A173: Mrs OBASOOTO ABIGAEL O. | B173: 0 | C173: 178 | E173: AMINU T. | F173: 7479.78
A174: OMONIYI OLUSOLA O. | B174: 0 | C174: 179 | E174: S. G. OGUNSANYA | F174: 3399.9
A175: BELLO AZEEZ A. | B175: 0 | C175: 180 | E175: OYERINDE A. M. | F175: 7479.78
A176: OLASUPO OLUFEMI S. | B176: 0 | C176: 181 | E176: R. K. AREMU | F176: 7479.78
A177: OYEDOTUN ISIAKA | B177: 0 | C177: 182 | E177: ABIDOGUN ADENIKE V. | F177: 3399.9
A178: JAIYEOBA OLURANTI A. | C178: 183 | E178: OKOFOR IFEOLUWA O. | F178: 3399.9
A179: OKETOKI A.F | B179: 3399.95 | C179: 184 | E179: ABIOLA MUJIDAT D. | F179: 10199.7
A180: AFOLABI JAMES O. | B180: 0 | C180: 185 | E180: OWOADE Y.O | F180: 7479.78
A181: AMUSA TAOFEEK A. | B181: 0 | C181: 186 | E181: MR. S. A. ADEJINMI | F181: 7479.78
...

Sheet Sheet4
B1: STAFF NAME | C1: staff' Name | D1: Car Loan | F1: S/N | G1: staff' Name | H1: Car Loan | I1: S/N | J1: STAFF NAME | K1: MONTHLY DED N
A2: 1 | B2: ADETEJU MISBAUDEEN A. | C2: ADETEJU MISBAUDEEN A. | D2: 11333 | F2: 1 | G2: ODETUNDE A. O. | H2: 11333 | I2: 1 | J2: MRS. ODETUNDE A. O. | K2: 11333 | L2: =K2-H2 -> 0
A3: 2 | B3: ADENIRAN ADEWALE O | C3: ADENIRAN ADEWALE O | D3: 10199.7 | F3: 3 | G3: ADENIRAN ADEWALE O | H3: 10199.7 | I3: 3 | J3: ADENIRAN ADEWALE O | K3: 10199.7 | L3: =K3-H3 -> 0
A4: 3 | B4: LAMIDI-HUSSEIN K. O | C4: LAMIDI-HUSSEIN K. O | D4: 10199.7 | F4: 5 | G4: LAMIDI-HUSSEIN K. O | H4: 10199.7 | I4: 4 | J4: LAMIDI-HUSSEIN K. O | K4: 10199.7 | L4: =K4-H4 -> 0
A5: 4 | B5: OLANIYAN OLUYEMI | C5: OLANIYAN OLUYEMI | D5: 10199.7 | F5: 6 | G5: OLANIYAN OLUYEMI | H5: 10199.7 | I5: 5 | J5: OLANIYAN OLUYEMI | K5: 10199.7 | L5: =K5-H5 -> 0
A6: 5 | B6: MORADEYO I. I. | C6: MORADEYO I. I. | D6: 7479.78 | F6: 8 | G6: MORADEYO I. I. | H6: 7479.78 | I6: 6 | J6: MORADEYO I. I. | K6: 7479.78 | L6: =K6-H6 -> 0
A7: 6 | B7: ADENUGA JUMOKE A. | C7: ADENUGA JUMOKE A. | D7: 7479.78 | F7: 9 | G7: ADENUGA JUMOKE A. | H7: 7479.78 | I7: 7 | J7: ADENUGA JUMOKE A. | K7: 7479.78 | L7: =K7-H7 -> 0
A8: 7 | B8: OLAGUNJU F. O. | C8: OLAGUNJU F. O. | D8: 7479.78 | F8: 10 | G8: OLAGUNJU F. O. | H8: 7479.78 | I8: 8 | J8: OLAGUNJU F. O. | K8: 7479.78 | L8: =K8-H8 -> 0
A9: 8 | B9: LAWAL ADENIKE M. | C9: LAWAL ADENIKE M. | D9: 7479.78 | F9: 12 | G9: LAWAL ADENIKE M. | H9: 7479.78 | I9: 9 | J9: LAWAL ADENIKE M. | K9: 7479.78 | L9: =K9-H9 -> 0
A10: 9 | B10: ALABI FUNMILAYO S. | C10: ALABI FUNMILAYO S. | D10: 7479.78 | F10: 15 | G10: ABIFARIN TOYIN | H10: 7479.78 | I10: 10 | J10: ABIFARIN TOYIN | K10: 7479.78 | L10: =K10-H10 -> 0
A11: 10 | B11: ADEGOKE SAMSON A. | C11: ADEGOKE SAMSON A. | D11: 3399.9 | F11: 19 | G11: ALABI FUNMILAYO S. | H11: 7479.78 | I11: 11 | J11: ALABI FUNMILAYO S. | K11: 7479.78 | L11: =K11-H11 -> 0
A12: 11 | B12: KAREEM SHAKIRUDEEN O. | C12: KAREEM SHAKIRUDEEN O. | D12: 1699.95 | F12: 22 | G12: ADEGOKE SAMSON A. | H12: 3399.9 | I12: 12 | J12: ADEGOKE SAMSON A. | K12: 3399.9 | L12: =K12-H12 -> 0
A13: 12 | B13: MR. I. J. OLAGUNJU | C13: AKINDUNNI OLUWAJUMOKE A. | D13: 7479.78 | F13: 25 | G13: KAREEM SHAKIRUDEEN O. | H13: 1699.95 | I13: 13 | J13: KAREEM SHAKIRUDEEN O. | K13: 1699.95 | L13: =K13-H13 -> 0
... A26: 25 | B26: RAJI H. M. | C26: RAJI H. M. | D26: 11333 | F26: 28 | G26: RAJI H. M. | H26: 11333 | I26: 26 | J26: RAJI H. M. | K26: 11333 | L26: =K26-H26 -> 0
A27: 26 | B27: ADEOSUN OLUSOLA O. | D27: 0 | F27: 41 | G27: AJAGUNA M. T. | H27: 10199.7 | I27: 27 | J27: AJAGUNA M. T. | K27: 10199.7 | L27: =K27-H27 -> 0
A28: 27 | B28: SOLE G. A. | C28: SOLE G. A. | D28: 3739.89 | F28: 48 | G28: OLASUNKANMI A. | H28: 10199.7 | I28: 28 | J28: OLASUNKANMI A. | K28: 10199.7 | L28: =K28-H28 -> 0
A29: 28 | B29: AJAGUNA M. T. | C29: AJAGUNA M. T. | D29: 10199.7 | F29: 58 | G29: FAWOLE T. O. | H29: 7479.78 | I29: 29 | J29: FAWOLE TAIWO | K29: 7479.78 | L29: =K29-H29 -> 0
A30: 29 | B30: OLASUNKANMI A. | C30: OLASUNKANMI A. | D30: 10199.7 | F30: 66 | G30: AKINLABI O. M. | H30: 3399.9 | I30: 30 | J30: O. M. AKINLABI | K30: 3399.9 | L30: =K30-H30 -> 0
A31: 30 | B31: FAWOLE TAIWO | C31: FAWOLE T. O. | D31: 7479.78 | F31: 3 | G31: OLUSANYA FLORENCE O. | H31: 10199.7 | I31: 31 | J31: OLUSANYA FLORENCE O. | K31: 10199.7 | L31: =K31-H31 -> 0
A32: 31 | B32: O. M. AKINLABI | C32: AKINLABI O. M. | D32: 3399 | F32: 11 | G32: SALAMI W. A. | H32: 7479.78 | I32: 32 | J32: SALAMI W. A. | K32: 7479.78 | L32: =K32-H32 -> 0
A33: 32 | B33: OLUSANYA FLORENCE O. | C33: OLUSANYA FLORENCE O. | D33: 10199.7 | F33: 12 | G33: SAMUEL PATIENCE C. | H33: 7479.78 | I33: 33 | J33: SAMUEL PATIENCE C. | K33: 7479.78 | L33: =K33-H33 -> 0
A34: 33 | B34: OLANIYI TITILAYO | D34: 0 | F34: 13 | G34: ADESAMI MODUPELOLA M. | H34: 7479.78 | I34: 34 | J34: ADESAMI MODUPELOLA M. | K34: 7479.78 | L34: =K34-H34 -> 0
A35: 34 | B35: SALAMI W. A. | C35: SALAMI W. A. | D35: 7479.78 | F35: 16 | G35: OLAITAN LANRE IYIOLA | H35: 7479.78 | I35: 35 | J35: OLAITAN LANRE IYIOLA | K35: 7479.78 | L35: =K35-H35 -> 0
A36: 35 | B36: SAMUEL PATIENCE C. | C36: SAMUEL PATIENCE C. | D36: 7479.78 | F36: 17 | G36: OLAWORE MICHEAL F. | H36: 7479.78 | I36: 36 | J36: OLAWORE MICHEAL F. | K36: 7479.78 | L36: =K36-H36 -> 0
A37: 36 | B37: ADESAMI MODUPELOLA M. | C37: ADESAMI MODUPELOLA M. | D37: 7479.78 | F37: 20 | G37: AFOLABI MARY A. | H37: 3399.9 | I37: 37 | J37: AFOLABI MARY A. | K37: 3399.9 | L37: =K37-H37 -> 0
A38: 37 | B38: OLAITAN LANRE IYIOLA | C38: OLAITAN LANRE IYIOLA | D38: 7479.78 | F38: 28 | G38: MOJEED T. A | H38: 3399.9 | I38: 38 | J38: MRS. T. A. MOJEED | K38: 3399.9 | L38: =K38-H38 -> 0
A39: 38 | B39: OLAWORE MICHEAL F. | C39: OLAWORE MICHEAL F. | D39: 7479.78 | F39: 29 | G39: MOSOMI OLUWAFUNKE | H39: 3399.9 | I39: 39 | J39: MOSOMI OLUWAFUNKE | K39: 3399.9 | L39: =K39-H39 -> 0
A40: 39 | B40: AFOLABI MARY A. | C40: AFOLABI MARY A. | D40: 3399.9 | F40: 1 | G40: OLATUNJI-DANIEL A. A. | H40: 11333 | I40: 40 | J40: OLATUNJI-DANIEL A. A. | K40: 11333 | L40: =K40-H40 -> 0
A41: 40 | B41: MRS. T. A. MOJEED | C41: MOJEED T. A | D41: 3399.9 | F41: 5 | G41: AKINYELE A. A.,O. | H41: 11333 | I41: 41 | J41: AKINYELE A. A.,O. | K41: 11333 | L41: =K41-H41 -> 0
A42: 41 | B42: MOSOMI OLUWAFUNKE | C42: MOSOMI OLUWAFUNKE | D42: 3399.9 | F42: 10 | G42: EBELOKU-MUSTAPHA R. A. | H42: 11333 | I42: 42 | J42: EBELOKU-MUSTAPHA R. A. | K42: 11333 | L42: =K42-H42 -> 0
A43: 42 | B43: ONIBIYO ABIMBOLA. A. | C43: ONIBIYO ABIMBOLA. A. | D43: 1699.95 | F43: 11 | G43: BAMIRO M. A. | H43: 11333 | I43: 43 | J43: BAMIRO M. A. | K43: 11333 | L43: =K43-H43 -> 0
A44: 43 | B44: OLATUNJI-DANIEL A. A. | C44: OLATUNJI-DANIEL A. A. | D44: 11333 | F44: 12 | G44: ODEMAKINDE B. S. | H44: 11333 | I44: 44 | J44: MRS. B.S. ODEMAKINDE | K44: 11333 | L44: =K44-H44 -> 0
A45: 44 | B45: ADIO M. O. | C45: ADIO M. O. | D45: 11333 | F45: 14 | G45: ADEBOYA O. O. | H45: 10199.7 | I45: 45 | J45: ADEBOYA O. O. | K45: 10199.7 | L45: =K45-H45 -> 0
A46: 45 | B46: OGUNRIN O. A. | C46: OGUNRIN O. A. | D46: 5666.5 | F46: 16 | G46: FALANA V. O. | H46: 10199.7 | I46: 46 | J46: FALANA V. O. | K46: 10199.7 | L46: =K46-H46 -> 0
... A70: 69 | B70: BAKARE A. T. | C70: BAKARE A. T. | D70: 16999.5 | F70: 11 | G70: ADEGBAYI I. A. | H70: 7479.78 | I70: 70 | J70: ADEGBAYI I. A. | K70: 7479.78 | L70: =K70-H70 -> 0
A71: 70 | B71: Mr A. A. Ipaye | D71: 0 | F71: 13 | G71: OSINEYE S. G. | H71: 7479.78 | I71: 71 | J71: MR. S. G. OSINEYE | K71: 7479.78 | L71: =K71-H71 -> 0
A72: 71 | B72: ADEGBAYI I. A. | C72: ADEGBAYI I. A. | D72: 7479.78 | F72: 14 | G72: OYINLOLA R. T. | H72: 7479.78 | I72: 72 | J72: OYINLOLA R. T. | K72: 7479.78 | L72: =K72-H72 -> 0
A73: 72 | B73: OLAGUNJU K. A. | C73: OLAGUNJU K. A. | D73: 7479.78 | F73: 15 | G73: TIJANI S. D. | H73: 7479.78 | I73: 73 | J73: TIJANI S. D. | K73: 7479.78 | L73: =K73-H73 -> 0
A74: 73 | B74: OYINLOLA R. T. | C74: OYINLOLA R. T. | D74: 7479.78 | F74: 18 | G74: ALAO O. O. | H74: 7479.78 | I74: 74 | J74: MR. O. O. ALAO | K74: 7479.78 | L74: =K74-H74 -> 0
A75: 74 | B75: TIJANI S. D. | C75: TIJANI S. D. | D75: 7479.78 | F75: 19 | G75: ONI OLUWABUNMI E. | H75: 7479.78 | I75: 75 | J75: ONI OLUWABUNMI E. | K75: 7479.78 | L75: =K75-H75 -> 0
A76: 75 | B76: YUSUFF K. A. | D76: 0 | F76: 20 | G76: ONI SEGUN | H76: 7479.78 | I76: 76 | J76: SEGUN ONI | K76: 7479.78 | L76: =K76-H76 -> 0
A77: 76 | B77: MR. O. O. ALAO | C77: ALAO O. O. | D77: 7479.78 | F77: 3 | G77: BAJELA A. O. | H77: 7479.78 | I77: 77 | J77: BAJELA A. O. | K77: 7479.78 | L77: =K77-H77 -> 0
A78: 77 | B78: ONI OLUWABUNMI E. | C78: ONI OLUWABUNMI E. | D78: 7479.78 | F78: 11 | G78: ADEYEMO G. | H78: 7479.78 | I78: 78 | J78: ADEYEMO G. | K78: 7479.78 | L78: =K78-H78 -> 0
A79: 78 | B79: SEGUN ONI | C79: ONI SEGUN | D79: 7479.78 | F79: 15 | G79: SALAU L. A. | H79: 7479.78 | I79: 79 | J79: SALAU L. A. | K79: 7479.78 | L79: =K79-H79 -> 0
A80: 79 | B80: SUNMONU W. B. | C80: SUNMONU W. B. | D80: 1699.95 | F80: 16 | G80: AJALA O. | H80: 7479.78 | I80: 80 | J80: AJALA O. | K80: 7479.78 | L80: =K80-H80 -> 0
A81: 80 | B81: BAJELA A. O. | C81: BAJELA A. O. | D81: 7479.78 | F81: 1 | G81: AWE A. L. | H81: 10046.44 | I81: 81 | J81: MR. A. L.AWE | K81: 10046.44 | L81: =K81-H81 -> 0
A82: 81 | B82: AYINDE O. | C82: AYINDE O. | D82: 1699.95 | F82: 8 | G82: FAGBAYIMU A. G. | H82: 7479.78 | I82: 82 | J82: FAGBAYIMU A. G. | K82: 7479.78 | L82: =K82-H82 -> 0
A83: 82 | B83: ADEYEMO G. | C83: ADEYEMO G. | D83: 7479.78 | F83: 1 | G83: ABASS A. I. | H83: 7479.78 | I83: 83 | J83: ABASS A. I. | K83: 7479.78 | L83: =K83-H83 -> 0
A84: 83 | B84: ABASS A. I. | C84: ABASS A. I. | D84: 7479.78 | F84: 2 | G84: ADELEYE M. E. | H84: 7479.78 | I84: 84 | J84: ADELEYE M. E. | K84: 7479.78 | L84: =K84-H84 -> 0
A85: 84 | B85: ADELEYE M. E. | C85: ADELEYE M. E. | D85: 7479.78 | F85: 3 | G85: BAMIGBOLA A. L. | H85: 7479.78 | I85: 85 | J85: BAMIGBOLA A. L. | K85: 7479.78 | L85: =K85-H85 -> 0
A86: 85 | B86: BAMIGBOLA A. L. | C86: BAMIGBOLA A. L. | D86: 7479.78 | F86: 4 | G86: GEORGE E. O. | H86: 7479.78 | I86: 86 | J86: GEORGE E. O. | K86: 7479.78 | L86: =K86-H86 -> 0
A87: 86 | B87: GEORGE E. O. | C87: GEORGE E. O. | D87: 7479.78 | F87: 16 | G87: SUNMON OLAMILETRILLION O. | H87: 7479.78 | I87: 87 | J87: O. O. SUNMONU | K87: 7479.78 | L87: =K87-H87 -> 0
A88: 87 | B88: O. O. SUNMONU | D88: 0 | F88: 7 | G88: OWOADE OBEMBE. S. | H88: 7479.98 | I88: 88 | J88: OWOADE OBEMBE. S. | K88: 7479.98 | L88: =K88-H88 -> 0
A89: 88 | B89: OWOADE OBEMBE. S. | C89: OWOADE OBEMBE. S. | D89: 7479.98 | F89: 8 | G89: OYELADE O. T. | H89: 7479.78 | I89: 89 | J89: OYELADE O. T. | K89: 7479.78 | L89: =K89-H89 -> 0
A90: 89 | B90: OYELADE O. T. | C90: OYELADE O. T. | D90: 7479.78 | F90: 13 | G90: LADEOKIN M. A. | H90: 7479.78 | I90: 90 | J90: LADEOKIN M. A. | K90: 7479.78 | L90: =K90-H90 -> 0
A91: 90 | B91: LADEOKIN M. A. | C91: LADEOKIN M. A. | D91: 7479.78 | F91: 25 | G91: ABIOLA GANIYAT A. | H91: 7479.78 | I91: 91 | J91: ABIOLA GANIYAT A. | K91: 7479.78 | L91: =K91-H91 -> 0
A92: 91 | B92: OLAWALE-WAHAB I. | C92: OLAWALE-WAHAB I. | D92: 3739.89 | F92: 27 | G92: OJO O. A. | H92: 3399.9 | I92: 92 | J92: OJO O. A. | K92: 3399.9 | L92: =K92-H92 -> 0
A93: 92 | B93: MARTINS G. | C93: SUNMON OLAMILETRILLION O. | D93: 7479.78 | I93: 93 | J93: ADEBIYI-AJALA T.O | K93: 0 | L93: =K93-H93 -> 0
A94: 93 | B94: ADEDIRAN J.O | C94: ADEDIRAN J.O | D94: 3399.9 | F94: 30 | G94: ADEYEMI B. F. | H94: 7479.78 | I94: 94 | J94: MRS. B. F. ADEYEMI | K94: 7479.78 | L94: =K94-H94 -> 0
A95: 94 | B95: ABIOLA GANIYAT A. | C95: ABIOLA GANIYAT A. | D95: 7479.78 | F95: 31 | G95: AJAYI B. J. | H95: 6799.8 | I95: 95 | J95: AJAYI B. J. | K95: 6799.8 | L95: =K95-H95 -> 0
A96: 95 | B96: OJO O. A. | C96: OJO O. A. | D96: 3399.9 | F96: 33 | G96: AYANNIRAN O. | H96: 7479.78 | I96: 96 | J96: AYANNIRAN O. | K96: 7479.78 | L96: =K96-H96 -> 0
A97: 96 | B97: ADEBIYI-AJALA T.O | C97: ADEBIYI-AJALA T.O | D97: 3399.9 | F97: 34 | G97: ESORUN T. | H97: 3399.9 | I97: 97 | J97: ESORUN T. | K97: 3399.9 | L97: =K97-H97 -> 0
A98: 97 | B98: MRS. B. F. ADEYEMI | C98: ADEYEMI B. F. | D98: 7479.78 | F98: 35 | G98: OKULAJA A. F., B. | H98: 7479.78 | I98: 98 | J98: OKULAJA A. F., B. | K98: 7479.78 | L98: =K98-H98 -> 0
A99: 98 | B99: AJAYI B. J. | C99: AJAYI B. J. | D99: 3399.9 | F99: 36 | G99: OLAIYAPO I. B. | H99: 3399.9 | I99: 99 | J99: OLAIYAPO I. B. | K99: 3399.9 | L99: =K99-H99 -> 0
A100: 99 | B100: AYANNIRAN O. | C100: AYANNIRAN O. | D100: 7479.78 | F100: 23 | G100: SANGOBIYI H. K. | H100: 11879.78 | I100: 100 | J100: MRS. H. K. SANGOBIYI | K100: 11879.78 | L100: =K100-H100 -> 0
A101: 100 | B101: ESORUN T. | C101: ESORUN T. | D101: 3399.9 | F101: 48 | G101: ALAO J. O. | H101: 3399.9 | I101: 101 | J101: MR. J. O. ALAO | K101: 3399.9 | L101: =K101-H101 -> 0
A102: 101 | B102: OKULAJA A. F., B. | C102: OKULAJA A. F., B. | D102: 7479.78 | F102: 38 | G102: OLAPADE O. S. | H102: 3399.9 | I102: 102 | J102: OLAPADE O. S. | K102: 3399.9 | L102: =K102-H102 -> 0
A103: 102 | B103: OLAIYAPO I. B. | C103: OLAIYAPO I. B. | D103: 3399.9 | F103: 42 | G103: OLAYINKA A. | H103: 3399.9 | I103: 103 | J103: OLAYINKA A. | K103: 3399.9 | L103: =K103-H103 -> 0
A104: 103 | B104: OLAPADE O. S. | C104: OLAPADE O. S. | D104: 3399.9 | F104: 39 | G104: OMOTOSHO F. O. | H104: 7479.78 | I104: 104 | J104: MR. F. O. OMOTOSHO | K104: 7479.78 | L104: =K104-H104 -> 0
A105: 104 | B105: OLAYINKA A. | C105: OLAYINKA A. | D105: 3399.9 | F105: 16 | G105: OYEJIDE F. O. | H105: 10199.9 | I105: 105 | J105: OYEJIDE F. O. | K105: 10199.9 | L105: =K105-H105 -> 0
... A110: 109 | B110: ENIOLA E. O. | C110: ENIOLA E. O. | D110: 3399.9 | F110: 25 | G110: ENIOLA E. O. | H110: 3399.9 | I110: 110 | J110: ENIOLA E. O. | K110: 3399.9 | L110: =K110-H110 -> 0
A111: 110 | B111: OPEYEMI-AKORO O. R. | C111: OPEYEMI-AKORO O. R. | D111: 3399.9 | E111: * | F111: 3 | G111: OPEYEMI-AKORO O. R. | H111: 3399.9 | I111: 111 | J111: OPEYEMI-AKORO O. R. | K111: 3399.9 | L111: =K111-H111 -> 0
A112: 111 | B112: SHODE JELILI O. | C112: SHODE JELILI O. | D112: 7479.89 | E112: * | F112: 4 | G112: SHODE JELILI O. | H112: 7479.89 | I112: 112 | J112: SHODE JELILI O. | K112: 7479.89 | L112: =K112-H112 -> 0
A113: 112 | B113: QOSIM SAUDAT A. | C113: QOSIM SAUDAT A. | D113: 3399.9 | E113: * | F113: 12 | G113: ASOLO O. ADEBOLA | H113: 3399.9 | I113: 113 | J113: QOSIM SAUDAT A. | K113: 3399.9 | L113: =K113-H113 -> 0
A114: 115 | B114: ALADE O. S. | C114: ALADE O. S. | D114: 3399.9 | E114: * | F114: 14 | G114: QOSIM SAUDAT A. | H114: 3399.9 | I114: 114 | J114: ALADE O. S. | K114: 3399.9 | L114: =K114-H114 -> 0
A115: 116 | B115: ADAMS TAIWO | C115: ADAMS TAIWO | D115: 3399.9 | F115: 21 | G115: ABIOLA OYETUNDE | H115: 3399.9 | I115: 115 | J115: ADAMS TAIWO | K115: 3399.9 | L115: =K115-H115 -> 0
A116: 117 | B116: SEJINRIN KEMI C. | C116: SEJINRIN KEMI C. | D116: 3399.9 | E116: * | F116: 22 | G116: OLAIFA SUNMOLA | H116: 3399.9 | I116: 116 | J116: SEJINRIN KEMI C. | K116: 3399.9 | L116: =K116-H116 -> 0
A117: 118 | B117: EWUOLA GRACE A. | C117: EWUOLA GRACE A. | D117: 3399.9 | E117: * | F117: 28 | G117: ALADE O. S. | H117: 3399.9 | I117: 117 | J117: EWUOLA GRACE A. | K117: 3399.9 | L117: =K117-H117 -> 0
A118: 119 | B118: OJO ABIODUN | C118: OJO ABIODUN | D118: 3399.9 | F118: 29 | G118: HASSAN ELIZABETH O. | H118: 3399.9 | I118: 118 | J118: OJO ABIODUN | K118: 3399.9 | L118: =K118-H118 -> 0
A119: 120 | B119: E. O. HASSAN | C119: ELIZABETH HASSAN | D119: 3399.9 | F119: 39 | G119: ADAMS TAIWO | H119: 3399.9 | I119: 119 | J119: E. O. HASSAN | K119: 3399.9 | L119: =K119-H119 -> 0
A120: 121 | B120: O. A. ASOLO | C120: ASOLO O. ADEBOLA | D120: 3399.9 | F120: 40 | G120: SEJINRIN KEMI C. | H120: 3399.9 | I120: 120 | J120: O. A. ASOLO | K120: 3399.9 | L120: =K120-H120 -> 0
A121: 122 | B121: O. ABIOLA | C121: ABIOLA OYETUNDE | D121: 3399.9 | F121: 41 | G121: EWUOLA GRACE A. | H121: 3399.9 | I121: 121 | J121: O. ABIOLA | K121: 3399.9 | L121: =K121-H121 -> 0
A122: 123 | B122: S. OLAIFA | C122: OLAIFA SUNMOLA | D122: 3399.9 | F122: 43 | G122: OJO ABIODUN | H122: 3399.9 | I122: 122 | J122: S. OLAIFA | K122: 3399.9 | L122: =K122-H122 -> 0
A123: 124 | B123: MR. O. OSUNLANA | C123: OSUNLANA OLUSEYI | D123: 7479.78 | F123: 1 | G123: OLABAMIJI ADETUTU A. | H123: 7479.78 | I123: 123 | J123: OLABAMIJI ADETUTU | K123: 7479.78 | L123: =K123-H123 -> 0
A124: 125 | B124: SHOLAJA WAHEED A. | C124: SHOLAJA WAHEED A. | D124: 1699.95 | F124: 2 | G124: OSUNLANA O. | H124: 7479.78 | I124: 124 | J124: MR. O. OSUNLANA | K124: 7479.78 | L124: =K124-H124 -> 0
A125: 126 | B125: IBITOKUN AYODELE O. | C125: IBITOKUN AYODELE O. | D125: 3399.9 | F125: 17 | G125: IBITOKUN AYODELE O. | H125: 3399.9 | I125: 125 | J125: IBITOKUN AYODELE O. | K125: 3399.9 | L125: =K125-H125 -> 0
A126: 127 | B126: OLAJIRE FASILAT | C126: OLAJIRE FASILAT | D126: 3399.95 | F126: 18 | G126: OYINLOLA IDAYAT | H126: 3399.9 | I126: 126 | J126: MRS. I. OYINLOLA | K126: 3399.9 | L126: =K126-H126 -> 0
A127: 128 | B127: MRS. I. OYINLOLA | C127: OYINLOLA IDAYAT | D127: 3399.9 | F127: 26 | G127: OKETOKI A.F | H127: 3399.95 | I127: 127 | J127: OKETOKI A.F | K127: 3399.95 | L127: =K127-H127 -> 0
A128: 129 | B128: Mrs OBASOOTO ABIGAEL O. | C128: Mrs OBASOOTO ABIGAEL O. | D128: 1699.95 | F128: 29 | G128: BALOGUN ABIBAT A. | H128: 3399.9 | I128: 128 | J128: BALOGUN ABIBAT A. | K128: 3399.9 | L128: =K128-H128 -> 0
A129: 130 | B129: OYEDOTUN ISIAKA | C129: OYEDOTUN ISIAKA | D129: 1699.95 | F129: 34 | G129: OYESIJI JAMES MR. | H129: 3399.9 | I129: 129 | J129: OYESIJI JAMES MR. | K129: 3399.9 | L129: =K129-H129 -> 0
... A142: 143 | B142: MORRIS LOLA O. | C142: MORRIS LOLA O. | D142: 3399.95 | F142: 42 | G142: OLADOKUN JIMOH | H142: 3399.9 | I142: 142 | J142: MR. OLADOKUN JIMOH | K142: 3399.9 | L142: =K142-H142 -> 0
A143: 144 | B143: ODUFUWA-ABAYOMI O. A. | C143: ODUFUWA-ABAYOMI O. A. | D143: 7479.78 | F143: 62 | G143: ADESOLA OLUWATOBI D. | H143: 6799.8 | J143: MRS. O. D. ADESOLA | K143: 6779.8 | L143: =K143-H143 -> -20
A144: 145 | B144: ABIOYE N.HASSAN | C144: ABIOYE N.HASSAN | D144: 3399.9 | F144: 1 | G144: ODUFUWA-ABAYOMI O. A. | H144: 7479.78 | I144: 143 | J144: ODUFUWA-ABAYOMI O. A. | K144: 7479.78 | L144: =K144-H144 -> 0
A145: 146 | B145: ARANSI MUKAILA | C145: ARANSI MUKAILA | D145: 3399.9 | F145: 3 | G145: AFOLABI ABRAHAM | H145: 3399.9 | I145: 144 | J145: MR. AFOLABI ABRAHAM | K145: 3399.9 | L145: =K145-H145 -> 0
A146: 147 | B146: BELLO SAIDAT | C146: BELLO SAIDAT | D146: 3399.9 | F146: 4 | G146: ABIOYE N.HASSAN | H146: 3399.9 | I146: 145 | J146: ABIOYE N.HASSAN | K146: 3399.9 | L146: =K146-H146 -> 0
A147: 148 | B147: AJAYI ADEOLA O. | C147: AJAYI ADEOLA O. | D147: 3399.9 | F147: 5 | G147: ARANSI MUKAILA | H147: 3399.9 | I147: 146 | J147: ARANSI MUKAILA | K147: 3399.9 | L147: =K147-H147 -> 0
A148: 149 | B148: AYOOLA SAUDAT O. | C148: AYOOLA SAUDAT O. | D148: 3399.9 | F148: 9 | G148: BELLO SAIDAT | H148: 3399.9 | I148: 147 | J148: BELLO SAIDAT | K148: 3399.9 | L148: =K148-H148 -> 0
A149: 150 | B149: YEKEEN MOJEED | C149: YEKEEN MOJEED | D149: 3399.9 | F149: 12 | G149: AJAYI ADEOLA O. | H149: 3399.9 | I149: 148 | J149: AJAYI ADEOLA O. | K149: 3399.9 | L149: =K149-H149 -> 0
A150: 151 | B150: OLAYIWOLA R. A. | C150: OLAYIWOLA R. A. | D150: 3399.9 | F150: 15 | G150: AYOOLA SAUDAT O. | H150: 3399.9 | I150: 149 | J150: AYOOLA SAUDAT O. | K150: 3399.9 | L150: =K150-H150 -> 0
A151: 152 | B151: ONWUCHEKA I. | C151: ONWUCHEKA I. | D151: 3399.9 | F151: 19 | G151: YEKEEN MOJEED | H151: 3399.9 | I151: 150 | J151: MR. KADIRI MOHAMMED | K151: 3399.9 | L151: =K151-H151 -> 0
...

Sheet Sheet5
A1: 3 | B1: ADENIRAN ADEWALE O | C1: 10199.7 | D1: ADENIRAN ADEWALE O | E1: 10199.7
A2: 5 | B2: LAMIDI-HUSSEIN K. O | C2: 10199.7 | D2: LAMIDI-HUSSEIN K. O | E2: 10199.7
A3: 6 | B3: OLANIYAN OLUYEMI | C3: 10199.7 | D3: OLANIYAN OLUYEMI | E3: 10199.7
A4: 7 | B4: AKANBI A. G. | C4: 3739.89 | D4: AKANBI A. G. | E4: 3739.89
A5: 8 | B5: MORADEYO I. I. | C5: 7479.78 | D5: MORADEYO I. I. | E5: 7479.78
A6: 9 | B6: ADENUGA JUMOKE A. | C6: 7479.78 | D6: ADENUGA JUMOKE A. | E6: 7479.78
A7: 10 | B7: OLAGUNJU F. O. | C7: 7479.78 | D7: OLAGUNJU F. O. | E7: 7479.78
A8: 11 | B8: ABODERIN OLUSEYE | C8: 3739.89 | D8: ABODERIN OLUSEYE | E8: 3739.89
A9: 12 | B9: LAWAL ADENIKE M. | C9: 7479.78 | D9: LAWAL ADENIKE M. | E9: 7479.78
A10: 19 | B10: KAZALI KUDIRAT B. | C10: 3739.89 | D10: KAZALI KUDIRAT B. | E10: 3739.89
A11: 20 | B11: ALABI FUNMILAYO S. | C11: 7479.78 | D11: ALABI FUNMILAYO S. | E11: 7479.78
A12: 23 | B12: ADEGOKE SAMSON A. | C12: 3399.9 | D12: ADEGOKE SAMSON A. | E12: 3399.9
... A43: 50 | B43: AKANDE OLUWATOYIN A. | C43: 1699.95 | D43: AKANDE OLUWATOYIN A. | E43: 1699.95
D44: KOLAPO TAWA A. | E44: 10199.7
A45: 5 | B45: OLUSANYA FLORENCE O. | C45: 10199.7 | D45: OLUSANYA FLORENCE O. | E45: 10199.7
A46: 7 | B46: ODEJIDE HELEN K. | C46: 7479.78 | D46: ODEJIDE HELEN K. | E46: 7479.78
A47: 8 | B47: ADEOSUN KEHINDE | C47: 3739.89 | D47: ADEOSUN KEHINDE | E47: 3739.89
A48: 9 | B48: AREMU OLAYEMI MARY | C48: 3739.89 | D48: AREMU OLAYEMI MARY | E48: 3739.89
A49: 13 | B49: OLANIYI TITILAYO | C49: 3739.89 | D49: OLANIYI TITILAYO | E49: 3739.89
A50: 14 | B50: SALAMI W. A. | C50: 7479.78 | D50: SALAMI W. A. | E50: 7479.78
A51: 15 | B51: SAMUEL PATIENCE C. | C51: 7479.78 | D51: SAMUEL PATIENCE C. | E51: 7479.78
A52: 16 | B52: ADESAMI MODUPELOLA M. | C52: 7479.78 | D52: ADESAMI MODUPELOLA M. | E52: 7479.78
A53: 19 | B53: OLAITAN LANRE IYIOLA | C53: 7479.78 | D53: OLAITAN LANRE IYIOLA | E53: 7479.78
A54: 20 | B54: OLAWORE MICHEAL F. | C54: 7479.78 | D54: OLAWORE MICHEAL F. | E54: 7479.78
A55: 21 | B55: ADEJUMO TAIWO O. | C55: 3739.89 | D55: ADEJUMO TAIWO O. | E55: 3739.89
A56: 24 | B56: AFOLABI MARY A. | C56: 3399.9 | D56: AFOLABI MARY A. | E56: 3399.9
... A101: 7 | B101: LAWAL TIRIMISIYU A. | C101: 11333 | D101: MR. T. A. LAWAL | E101: 11333
D102: BAKARE A. T. | E102: 0
A103: 5 | B103: HAMMED S. O. | C103: 3739.89 | D103: HAMMED S. O. | E103: 3739.89
A104: 6 | B104: Mr A. A. Ipaye | C104: 3739.89 | D104: Mr A. A. Ipaye | E104: 3739.89
A105: 9 | B105: ODUNTAN O. E. | C105: 3739.89 | D105: ODUNTAN O. E. | E105: 3739.89
A106: 11 | B106: ISIAKA S. | C106: 3739.89 | D106: ISIAKA S. | E106: 3739.89
A107: 12 | B107: ADEGBAYI I. A. | C107: 7479.78 | D107: ADEGBAYI I. A. | E107: 7479.78
A108: 13 | B108: BAMIDELE A. A. | C108: 3739.89 | D108: BAMIDELE A. A. | E108: 3739.89
A109: 14 | B109: OLAGUNJU K. A. | C109: 7479.78 | D109: OLAGUNJU K. A. | E109: 7479.78
A110: 16 | B110: OYINLOLA R. T. | C110: 7479.78 | D110: OYINLOLA R. T. | E110: 7479.78
A111: 17 | B111: TIJANI S. D. | C111: 7479.78 | D111: TIJANI S. D. | E111: 7479.78
A112: 18 | B112: YUSUFF K. A. | C112: 3739.89 | D112: YUSUFF K. A. | E112: 3739.89
A113: 20 | B113: ALAO O. O. | C113: 7479.78
A114: 21 | B114: ONI OLUWABUNMI E. | C114: 7479.78 | D114: ONI OLUWABUNMI E. | E114: 7479.78
A115: 23 | B115: OYENIRAN S. | C115: 3739.89 | D115: OYENIRAN S. | E115: 3739.89
A116: 2 | B116: SUNMONU W. B. | C116: 1699.95 | D116: SUNMONU W. B. | E116: 1699.95
A117: 7 | B117: AYINDE O. | C117: 1699.95 | D117: AYINDE O. | E117: 1699.95
A118: 1 | B118: ABASS A. I. | C118: 7479.78 | D118: ABASS A. I. | E118: 7479.78
A119: 2 | B119: ADELEYE M. E. | C119: 7479.78 | D119: ADELEYE M. E. | E119: 7479.78
A120: 3 | B120: BAMIGBOLA A. L. | C120: 7479.78 | D120: BAMIGBOLA A. L. | E120: 7479.78
A121: 4 | B121: GEORGE E. O. | C121: 7479.78 | D121: ISMAIL A. M. | E121: 3739.89
A122: 5 | B122: ISMAIL A. M. | C122: 3739.89 | D122: OYELADE O. T. | E122: 7479.78
A123: 8 | B123: OYELADE O. T. | C123: 7479.78 | D123: LADEOKIN M. A. | E123: 7479.78
A124: 13 | B124: LADEOKIN M. A. | C124: 7479.78 | D124: OLAWALE-WAHAB I. | E124: 3739.89
A125: 15 | B125: OLAWALE-WAHAB I. | C125: 3739.89 | D125: MARTINS G. | E125: 3739.89
... A256: 7 | B256: ALADE J. | C256: 1699.95 | D256: ADEYEMO BISOLA | E256: 7479.78
C257: =SUM(C1:C256) -> 1267719.5 | D257: FADELE O.O. | E257: 3399.9
D258: ALADE J. | E258: 1699.95
D259: ADEYEMI B. F. | E259: 7479.78
A260: High Court of Justice, Ring Road, Ibadan. | E260: =SUM(E1:E259) -> 1283476.9
A261: HIGH COURT OF JUSTICE.
A262: ANALYSIS FOR THE MONTH OF AUGUST, 2016.
A263: NO | B263: SECTIONS | C263: Car Loan
A264: 1 | B264: G40 | C264: 120356.46
A265: 2 | B265: CR'S OFFICE | C265: 105396.9
A266: 3 | B266: LITIGATION A | C266: 92817.27 | D266: staff' Name | E266: LAST INSTALMENT MONTH AND YEAR
A267: 4 | B267: LITIGATION B | C267: 71057.91 | D267: MR. ABAYOMI OGUNDELE | E267: MARCH, 2012
A268: 5 | B268: LITIGATION C | C268: 3399.9 | D268: MRS. B. S. ODEMAKINDE | E268: APRIL, 2012
A269: 6 | B269: LITIGATION D | C269: 115483.27 | D269: MRS. OLANIYOMU O. ALICE | E269: JUNE, 2014
A270: 7 | B270: LITIGATION E | C270: 102335.54 | D270: MR. A. T. BAKARE | E270: APRIL, 2013
A271: 8 | B271: LITIGATION F | C271: 59498.25 | D271: MR. ROTIMI AWEDA | E271: -
A272: 9 | B272: LITIGATION G | C272: 50998.65 | D272: MRS. R. A. ADEJUWON | E272: SEPTEMBER, 2013
A273: 10 | B273: MAINTENANCE A | C273: 46918.62 | D273: MRS. V. M AROGUNDADE | E273: SEPTEMBER, 2013
A274: 11 | B274: MAINTENANCE B | C274: 79897.65 | D274: MRS. ENIOLA A ABIGAEL | E274: JUNE, 2013
A275: 12 | B275: MAINTENANCE C | C275: 66978.03 | D275: MRS. AKINTOLA S. ABIODUN | E275: AUGUST, 2013
A276: 13 | B276: MAINTENANCE D | C276: 0 | D276: MR. ADEMAKINWA KEHINDE B | E276: -
A277: 14 | B277: ACCOUNTS | C277: 86017.47 | D277: MR. ADEKUNLE MURUFU | E277: -
... A285: 22 | B285: PROTOCOL | C285: 30259.11 | D285: MR. BAKARE ADEGBOLA T. | E285: DECEMBER, 2014
B286: TOTAL | C286: 1267719.5 | D286: MRS. ADEKILE M.I. | E286: DECEMBER, 2014
A300: S/N | B300: BANK NAME
A301: 1 | B301: #REF!
A302: 2 | B302: 15
B303: CASH
A304: 3 | B304: #REF!
A305: 4 | B305: #REF!
A306: 5 | B306: #REF!
A307: 6 | B307: 19
A308: 7 | B308: #REF!
A309: 8 | B309: #REF!
A310: 9 | B310: #REF!
A311: 10 | B311: #REF!
A312: 11 | B312: #REF!
A313: 12 | B313: #REF!
A314: 13 | B314: #REF!
A315: 14 | B315: 15
A316: 15 | B316: 15
A317: 16 | B317: 0
A318: 17 | B318: 0
A319: 18 | B319: NAME:, _____________________________________
A320: 19 | B320: 15
B325: BANK NAME
B326: ACCESS BANK PLC.
B327: AWE MICROFINACE BANK PLC.
B328: CASH
...

Sheet Sheet6
A1: OLABAMIJI ADETUTU | B1: 330000 | C1: =B1*0.1333 -> 43989 | D1: =E1*F1 -> 373989 | E1: 50 | F1: 7479.78 | G1: *
A2: MR. O. OSUNLANA | B2: 330000 | C2: =B2*0.1333 -> 43989 | D2: =E2*F2 -> 373989 | E2: 50 | F2: 7479.78 | G2: *
A3: OKETOKI A.F | B3: 150000 | C3: =B3*0.1333 -> 19995 | D3: =E3*F3 -> 169997.5 | E3: 50 | F3: 3399.95 | G3: *
A4: BALOGUN ABIBAT A. | B4: 150000 | C4: =B4*0.1333 -> 19995 | D4: =E4*F4 -> 339990 | E4: 50 | F4: 6799.8 | G4: *
A5: MORRIS LOLA O. | B5: 150000 | C5: =B5*0.1333 -> 19995 | D5: =E5*F5 -> 169997.5 | E5: 50 | F5: 3399.95 | G5: *
A6: MR. SAHEED G. ABIOYE | B6: 330000 | C6: =B6*0.1333 -> 43989 | D6: =E6*F6 -> 373989 | E6: 50 | F6: 7479.78 | G6: *
A7: MRS. O. Y. ALUKO | B7: 150000 | C7: =B7*0.1333 -> 19995 | D7: =E7*F7 -> 169995 | E7: 50 | F7: 3399.9 | G7: *
A8: MRS. D. O. ABODUNDE | B8: 150000 | C8: =B8*0.1333 -> 19995 | D8: =E8*F8 -> 169995 | E8: 50 | F8: 3399.9 | G8: *
A9: MRS. R. A. OWOADE | B9: 330000 | C9: =B9*0.1333 -> 43989 | D9: =E9*F9 -> 373989 | E9: 50 | F9: 7479.78 | G9: *
A10: MRS. J. A. OWOADE | B10: 330000 | C10: =B10*0.1333 -> 43989 | D10: =E10*F10 -> 373989 | E10: 50 | F10: 7479.78 | G10: *
A11: MR. A. O. ADEFI | B11: 150000 | C11: =B11*0.1333 -> 19995 | D11: =E11*F11 -> 169995 | E11: 50 | F11: 3399.9 | G11: *
A12: MRS. Y. S. OGUNSIJI | B12: 150000 | C12: =B12*0.1333 -> 19995 | D12: =E12*F12 -> 169995 | E12: 50 | F12: 3399.9 | G12: *
... A20: MISS. ADEMOYE MARIAM F. | B20: 150000 | C20: =B20*0.1333 -> 19995 | D20: =E20*F20 -> 169995 | E20: 50 | F20: 3399.9 | G20: *
F21: =SUM(F1:F20) -> 110507.06
F22: 107107.16
F23: =F21-F22 -> 3399.9

Sheet Sheet7
A2: S/N | B2: REF. I.D | C2: STAFF NAME | D2: MONTHLY DED N | E2: S/N | F2: staff' Name | G2: Car Loan
A3: 1 | B3: 0 | C3: MRS. ODETUNDE A. O. | D3: 11333 | E3: 1 | F3: ODETUNDE A. O. | G3: 11333
A4: 2 | B4: 0 | C4: LAMIDI-HUSSEIN K. O | D4: 10199.7 | E4: 3 | F4: LAMIDI-HUSSEIN K. O | G4: 10199.7
A5: 4 | B5: 0 | C5: ADENUGA JUMOKE A. | D5: 7479.78 | E5: 6 | F5: ADENUGA JUMOKE A. | G5: 7479.78
A6: 5 | B6: 0 | C6: MR. OLUSEYE ABODERIN | D6: 10199.7 | E6: 7 | F6: ABODERIN OLUSEYE | G6: 10199.7
A7: 6 | B7: 0 | C7: LAWAL ADENIKE M. | D7: 10000 | E7: 8 | F7: LAWAL ADENIKE M. | G7: 10000
A8: 7 | B8: 0 | C8: ABIFARIN TOYIN | D8: 7479.78 | E8: 11 | F8: ABIFARIN TOYIN | G8: 7479.78
A9: 8 | B9: 0 | C9: ALABI FUNMILAYO S. | D9: 7479.78 | E9: 15 | F9: ALABI FUNMILAYO S. | G9: 7479.78
A10: 9 | B10: 0 | C10: AKINDUNNI OLUWAJUMOKE A. | D10: 7479.78 | E10: 4 | F10: AKINDUNNI OLUWAJUMOKE A. | G10: 7479.78
A11: 10 | B11: 0 | C11: MR. I. J. OLAGUNJU | D11: 7479.78 | E11: 7 | F11: OLAGUNJU IBUKUN J. | G11: 7479.78
A12: 11 | B12: 0 | C12: BABALOLA AINA O. | D12: 3399.9 | E12: 13 | F12: BABALOLA AINA O. | G12: 3399.9
A13: 12 | B13: 0 | C13: IWUNOR OLUBISI O. | D13: 7479.78 | E13: 3 | F13: IWUNOR OLUBISI O. | G13: 7479.78
A14: 13 | B14: 0 | C14: OLAGUNJU ESTHER A. | D14: 7479.78 | E14: 4 | F14: OLAGUNJU ESTHER A. | G14: 7479.78
... A33: 32 | B33: 0 | C33: OLAITAN LANRE IYIOLA | D33: 7479.78 | E33: 12 | F33: OLAITAN LANRE IYIOLA | G33: 7479.78
A34: 33 | C34: OLAWORE MICHEAL F. | D34: 7479.78 | E34: 13 | F34: OLAWORE MICHEAL F. | G34: 7479.78
A35: 34 | B35: 0 | C35: MRS. TAIWO O. ADEJUMO | D35: 7479.78 | E35: 14 | F35: ADEJUMO TAIWO O. | G35: 7479.78
A36: 35 | B36: 0 | C36: AFOLABI MARY A. | D36: 3399.9 | E36: 16 | F36: AFOLABI MARY A. | G36: 3399.9
A37: 36 | B37: 0 | C37: MRS. T. A. MOJEED | D37: 3399.9 | E37: 22 | F37: MOJEED T. A | G37: 3399.9
A38: 37 | B38: 0 | C38: MOSOMI OLUWAFUNKE | D38: 3399.9 | E38: 23 | F38: MOSOMI OLUWAFUNKE | G38: 3399.9
A39: 38 | B39: 0 | C39: AKINYELE A. A.,O. | D39: 11333 | E39: 4 | F39: AKINYELE A. A.,O. | G39: 11333
A40: 39 | C40: MRS. B.S. ODEMAKINDE | D40: 11333 | E40: 11 | F40: ODEMAKINDE B. S. | G40: 11333
A41: 40 | C41: MR. MARTINS K. O. | D41: 10199.7 | E41: 12 | F41: MARTINS K. O. | G41: 10199.7
A42: 41 | B42: 0 | C42: ADEBOYA O. O. | D42: 10199.7 | E42: 13 | F42: ADEBOYA O. O. | G42: 10199.7
A43: 42 | B43: 0 | C43: FALANA V. O. | D43: 10199.7 | E43: 15 | F43: FALANA V. O. | G43: 10199.7
A44: 43 | B44: 0 | C44: E. T. OYENIRAN | D44: 7479.78 | E44: 19 | F44: OYENIRAN E. T. | G44: 7479.78
A45: 44 | B45: 0 | C45: OLANIYAN O. | D45: 7479.78 | E45: 22 | F45: MR. O.OLANIYAN | G45: 7479.78
A46: 45 | B46: 0 | C46: ADEBAYO O. T. | D46: 7479.78 | E46: 24 | F46: ADEBAYO O. T. | G46: 7479.78
A47: 46 | B47: 0 | C47: KAZEEM OLUJOKE | D47: 11333 | E47: 1 | F47: KAZEEM OLUJOKE | G47: 11333
A48: 47 | B48: 0 | C48: MRS. A. YUSUFF | D48: 7479.78 | E48: 2 | F48: YUSUFF ADIJAT | G48: 7479.78
A49: 48 | B49: 0 | C49: OLANIYAN MISTURA B. | D49: 7479.78 | E49: 4 | F49: OLANIYAN MISTURA B. | G49: 7479.78
A50: 49 | B50: 0 | C50: FOLORUNSO. O. MODUPE | D50: 7479.78 | E50: 2 | F50: FOLORUNSO. O. MODUPE | G50: 7479.78
A51: 50 | B51: 0 | C51: ALADE VICTORIA A. | D51: 7479.78 | E51: 5 | F51: ALADE VICTORIA A. | G51: 7479.78
A52: 51 | B52: 0 | C52: SALAMI TOYIN O. | D52: 7479.78 | E52: 6 | F52: SALAMI TOYIN O. | G52: 7479.78
A53: 52 | B53: 0 | C53: MR. A. ESAN | D53: 7479.78 | E53: 7 | F53: ESAN ADENRELE | G53: 7479.78
... A59: 58 | B59: 0 | C59: MR. S. T. AMOO | D59: 10199.7 | E59: 14 | F59: AMOO S.T | G59: 10199.7
A60: 59 | C60: MRS. A. T. TIJANI | D60: 7479.78 | E60: 18 | F60: Mrs A. T. Tijani | G60: 7479.78
A61: 60 | B61: 0 | C61: BAKARE A. T. | D61: 15999.75 | E61: 2 | F61: BAKARE A. T. | G61: 15999.75
A62: 61 | B62: 0 | C62: LAWAL F. A. | D62: 7479.78 | E62: 6 | F62: LAWAL F. A. | G62: 7479.78
A63: 62 | B63: 0 | C63: SAFIU-OLALERE S, K | D63: 7479.78 | E63: 9 | F63: MRS. M.K. SAFIU OLALERE | G63: 7479.78
A64: 63 | B64: 0 | C64: ADEGBAYI I. A. | D64: 7479.78 | E64: 11 | F64: ADEGBAYI I. A. | G64: 7479.78
A65: 64 | B65: 0 | C65: MR. S. G. OSINEYE | D65: 7479.78 | E65: 13 | F65: OSINEYE S. G. | G65: 7479.78
A66: 65 | B66: 0 | C66: TIJANI S. D. | D66: 7479.78 | E66: 15 | F66: TIJANI S. D. | G66: 7479.78
A67: 66 | B67: 0 | C67: MR. O. O. ALAO | D67: 7479.78 | E67: 18 | F67: ALAO O. O. | G67: 7479.78
A68: 67 | B68: 0 | C68: MR. A. L.AWE | D68: 10046.44 | E68: 1 | F68: AWE A. L. | G68: 10046.44
A69: 68 | B69: 0 | C69: BAJELA A. O. | D69: 7479.78 | E69: 3 | F69: BAJELA A. O. | G69: 7479.78
A70: 69 | B70: 0 | C70: FAGBAYIMU A. G. | D70: 7479.78 | E70: 8 | F70: FAGBAYIMU A. G. | G70: 7479.78
A71: 70 | B71: 0 | C71: ADEYEMO G. | D71: 7479.78 | E71: 11 | F71: ADEYEMO G. | G71: 7479.78
A72: 71 | B72: 0 | C72: AJALA O. | D72: 7479.78 | E72: 14 | F72: AJALA O. | G72: 7479.78
... A87: 86 | B87: 0 | C87: OLAPADE O. S. | D87: 3399.76 | E87: 34 | F87: OLAPADE O. S. | G87: 3399.76
A88: 87 | C88: MR. F. O. OMOTOSHO | D88: 7479.78 | E88: 35 | F88: OMOTOSHO F. O. | G88: 7479.78
A89: 88 | C89: OLAYINKA A. | D89: 3399.9 | E89: 37 | F89: OLAYINKA A. | G89: 3399.9
A90: 89 | C90: MR. J. O. ALAO | D90: 3399.9 | E90: 40 | F90: ALAO J. O. | G90: 3399.9
C91: MRS. E. M. ABEGUNDE | D91: 10199.9 | E91: 8 | F91: ABEGUNDE E. M. | G91: 10199.9
A92: 90 | B92: 0 | C92: MRS. M. O. AYOADE | D92: 7479.78 | E92: 10 | F92: AYOADE M. O. | G92: 7479.78
A93: 91 | B93: 0 | C93: OYEJIDE F. O. | D93: 10199.9 | E93: 15 | F93: OYEJIDE F. O. | G93: 10199.9
A94: 92 | B94: 0 | C94: ADEPOJU A. | D94: 7479.89 | E94: 16 | F94: ADEPOJU A. | G94: 7479.89
A95: 93 | B95: 0 | C95: BABATUNDE T. I. | D95: 7479.78 | E95: 17 | F95: BABATUNDE T. I. | G95: 7479.78
A96: 95 | C96: MRS. O. B. AYOOLA | D96: 11879.78 | E96: 20 | F96: AYOOLA O. B. | G96: 11879.78
A97: 96 | C97: MRS. E. O. OMOJUWA | D97: 14629.78 | E97: 21 | F97: OMOJUWA E. O. | G97: 14629.78
A98: 97 | B98: 0 | C98: SHODE JELILI O. | D98: 7479.89 | E98: 3 | F98: SHODE JELILI O. | G98: 7479.89
A99: 98 | B99: 0 | C99: O. A. ASOLO | D99: 3399.9 | E99: 10 | F99: ASOLO O. ADEBOLA | G99: 3399.9
A100: 99 | B100: 0 | C100: E. O. HASSAN | D100: 3399.9 | E100: 26 | F100: HASSAN ELIZABETH O. | G100: 3399.9
A101: 100 | B101: 0 | C101: MRS. OYEKALE | D101: 3399.9 | E101: 33 | F101: OYEKALE OLUGBADE | G101: 3399.9
A102: 101 | B102: 0 | C102: ADAMS TAIWO | D102: 3399.9 | E102: 35 | F102: ADAMS TAIWO | G102: 3399.9
A103: 102 | B103: 0 | C103: EWUOLA GRACE A. | D103: 3399.9 | E103: 37 | F103: EWUOLA GRACE A. | G103: 3399.9
A104: 103 | B104: 0 | C104: OLABAMIJI ADETUTU | D104: 7479.78 | E104: 1 | F104: OLABAMIJI ADETUTU A. | G104: 7479.78
A105: 104 | B105: 0 | C105: MR. O. OSUNLANA | D105: 7479.78 | E105: 2 | F105: OSUNLANA O. | G105: 7479.78
A106: 105 | B106: 0 | C106: MRS. M. O. YUSUFF | D106: 14629.78 | E106: 3 | F106: YUSUFF MUJIDAT O. | G106: 14629.78
A107: 106 | B107: 0 | C107: MR. SAHEED G. ABIOYE | D107: 7479.78 | E107: 5 | F107: ABIOYE SAHEED G. | G107: 7479.78
A108: 107 | B108: 0 | C108: MRS. ADELKE FOLASADE D | D108: 7479.78 | E108: 7 | F108: ADELEKE FOLASADE D. | G108: 7479.78
A109: 108 | B109: 0 | C109: MRS. R. A. OWOADE | D109: 7479.78 | E109: 9 | F109: OWOADE J. A | G109: 7479.78
... A117: 117 | B117: 0 | C117: MRS. D. O. ABODUNDE | D117: 3399.9 | E117: 40 | F117: ABODUNDE DOJA | G117: 3399.9
A118: 118 | C118: MRS. Y. S. OGUNSIJI | D118: 3399.9 | E118: 44 | F118: OGUNJIMI YETUNDE S. | G118: 3399.9
A119: 119 | C119: ADERINTO OLADUUNI | D119: 3399.9 | E119: 47 | F119: ADERINTO OLADUNNI A. | G119: 3399.9
A120: 120 | C120: MORRIS LOLA O. | D120: 3399.9 | E120: 48 | F120: MORRIS LOLA O. | G120: 3399.95
A121: 121 | C121: OLAYIWOLA BASIRAT | D121: 3399.9 | E121: 49 | F121: OLAYIWOLA BASIRAT | G121: 3399.9
C122: MRS. O. D. ADESOLA | D122: 6799.8 | E122: 53 | F122: ADESOLA OLUWATOBI D. | G122: 6799.8
A123: 122 | B123: 0 | C123: ODUFUWA-ABAYOMI O. A. | D123: 7479.78 | E123: 1 | F123: ODUFUWA-ABAYOMI O. A. | G123: 7479.78
A124: 123 | B124: 0 | C124: MR. AFOLABI ABRAHAM | D124: 3399.9 | E124: 3 | F124: AFOLABI ABRAHAM | G124: 3399.9
A125: 124 | B125: 0 | C125: ABIOYE N.HASSAN | D125: 0 | E125: 5 | F125: ARANSI MUKAILA | G125: 3399.9
A126: 125 | B126: 0 | C126: ARANSI MUKAILA | D126: 3399.9 | E126: 9 | F126: BELLO SAIDAT | G126: 3399.9
A127: 126 | B127: 0 | C127: BELLO SAIDAT | D127: 3399.9 | E127: 14 | F127: AYOOLA SAUDAT O. | G127: 3399.9
A128: 127 | B128: 0 | C128: AYOOLA SAUDAT O. | D128: 3399.9 | E128: 18 | F128: YEKEEN MOJEED | G128: 3399.9
A129: 128 | B129: 0 | C129: MR. KADIRI MOHAMMED | D129: 3399.9 | E129: 19 | F129: OLAYIWOLA R. A. | G129: 3399.9
A130: 129 | B130: 0 | C130: YEKEEN MOJEED | D130: 3399.9 | E130: 21 | F130: KADIRI MOHAMMED | G130: 3399.9
A131: 130 | B131: 0 | C131: OLAYIWOLA R. A. | D131: 3399.9 | E131: 26 | F131: OLATUNJI ADEREMI M. | G131: 3399.9
A132: 131 | B132: * | C132: OHU ABOSEDE | D132: 3399.9 | E132: 31 | F132: OHU ABOSEDE | G132: 3399.9
A133: 132 | C133: MR. OLATUNJI ADEREMI | D133: 3399.9 | E133: 35 | F133: SANNI OLUWOLE O. | G133: 3399.72
A134: 133 | C134: SANNI OLUWOLE O. | D134: 3399.72 | E134: 36 | F134: ADEGOKE GAFAR | G134: 3399.9
A135: 134 | C135: ADEGOKE GAFAR | D135: 3399.9 | E135: 39 | F135: ASAOLU OYEWOLE | G135: 3399.9
A136: 135 | C136: ASAOLU OYEWOLE | D136: 3399.9 | E136: 40 | F136: EWUOLA LAWRENCE | G136: 3399.9
A137: 136 | C137: EWUOLA LAWRENCE | D137: 3399.9 | E137: 41 | F137: HARUNA RILIWANU | G137: 3401.9
A138: 137 | C138: HARUNA RILIWANU | D138: 3401.9 | E138: 81 | F138: MR. SAMSON OJO | G138: 3399.9
A139: 138 | C139: MR. ONWUCHEKA I | D139: 3399.9 | E139: 82 | F139: MR. ONWUCHEKA I | G139: 3399.9
A140: 139 | C140: MR. SAMSON OJO | D140: 3399.9 | E140: 13 | F140: MUSTAPHA DAUDA | G140: 7479.78
A141: 140 | C141: MUSTAPHA DAUDA | D141: 7479.78 | E141: 16 | F141: ADEWOYIN ODUNOLA | G141: 3399.9
A142: 141 | C142: ADEDEJI YISAU | D142: 3399.9 | E142: 17 | F142: ADEDEJI YISAU | G142: 3399.9
A143: 142 | C143: O. ADEWOYIN | D143: 3399.9 | E143: 2 | F143: ABORISADE MOLIK | G143: 7479.78
A144: 143 | C144: ABORISADE MOLIK | D144: 7479.78 | E144: 4 | F144: LAMIDI RAMONI | G144: 7479.78
... A158: 158 | C158: MR. S. A. ADEJINMI | D158: 7479.78 | E158: 5 | F158: ADEJINMI SUNDAY A. | G158: 7479.78
...
